Workbook

Sheet 00 Cover
A1: MaxBid
A2: Strategic Project Workbook | maxbid.com.au
A4: Prepared for | B4: Ashleigh Phillips and Jason
A5: Version | B5: 0.1 Draft for review
A6: Date | B6: 22 September 2026
A7: Status | B7: Design phase. Visual design signed off on 22 September 2026. No build work until the full workbook is signed off.
A8: Design prototypes | B8: https://claude.ai/artifact/T6x3BarxFAz2nA7G7DyMAp The Chosen homepage and Main pages in this canvas are the signed off designs. Other pages in the canvas are explored options kept for reference.
A9: Purpose | B9: Single source of truth for what we are building: scope, features, valuation logic, data sources, database, tech stack, design, commercial model, risks and the build roadmap.
A10: How to use | B10: Each tab covers one topic. Tab 02 records every decision made, so any later change is made there first and flows into the other tabs. Tab 10 is a live calculator that proves the bid maths with formulas.
A11: Cell legend | B11: Blue text on yellow fill means an input you can change. Black text means a formula or fixed content. Values marked Estimate must be validated during the MVP.
A13: Contents
A14: 01 Summary | B14: Vision, problem, solution, positioning and MVP goals
A15: 02 Decisions | B15: Register of every decision made in the discovery session
A16: 03 Users | B16: Target users and personas
A17: 04 Competitors | B17: Existing tools and the gap we fill
A18: 05 Scope | B18: What is in V1, what is deferred and what is excluded
A19: 06 User Journey | B19: End to end workflow from catalogue link to recorded outcome
A20: 07 Features | B20: Full feature register with priority, phase and acceptance criteria
A21: 08 Matching Logic | B21: Match levels, evidence weighting, confidence scoring and resale scenarios
A22: 09 Cost Fields | B22: Every cost line in the calculator, its source and GST treatment
A23: 10 Profit Calculator | B23: Working model of the bid engine with live formulas and a sensitivity table
A24: 11 Data Sources | B24: Where every data point comes from and how it is obtained
A25: 12 Pipeline | B25: Processing stages, jobs, AI usage and outputs
... A52: 39 Build Architecture | B52: Monorepo, component library, file size rules, mobile first rules and performance budgets

Sheet 01 Summary
A1: Executive Summary
A3: Name | B3: MaxBid at maxbid.com.au. App at app.maxbid.com.au.
A4: Vision | B4: A decision support platform that turns any supported Australian auction catalogue into a ranked list of buying opportunities, each with evidenced market values, full acquisition costs and a safe maximum bid.
A5: Problem | B5: Resellers buying at auction guess at resale value, forget costs such as buyer's premium, GST, transport and repairs, and bid on emotion in the final seconds. Researching every lot manually across eBay, retailers and past auction results takes hours per catalogue.
A6: Solution | B6: Paste a catalogue link or upload a PDF. The platform extracts every lot, runs a fast triage to rank opportunities, then performs deep analysis on the lots the user shortlists. Deep analysis identifies the item using text and photos, finds comparable sold and advertised prices, explains exactly what each comparable is and how it differs, and calculates target, absolute maximum and break even bids against the user's own costs and profit goal.
A7: Core principle | B7: Transparency over false precision. Every value shows its evidence, the match level, the differences and a confidence rating. The system never presents a weak estimate as a verified value.
A8: Primary user | B8: Resellers and flippers buying at auction for profit in Australia.
A9: Launch sources | B9: Grays, Pickles and Lloyds, plus PDF catalogue upload as a universal fallback.
A10: Category scope | B10: All auction categories, using a category agnostic matching engine with category specific valuation rules added progressively.
A11: Build approach | B11: Built in house by Ashleigh using Claude Code and Codex on Next.js, Supabase and Vercel. Used internally first, commercialised once proven.
A12: MVP goal | B12: Internal MVP in six to eight weeks that we use on real auctions, recording actual outcomes to measure valuation accuracy before any public launch.
A13: Commercial path | B13: Subscription tiers with included deep analysis credits and top up packs. Free triage as the entry point.
A14: Defensibility | B14: The long term moat is the accumulated database of identified products, comparables, user corrections and verified sold outcomes. Every analysis makes the next one more accurate.

Sheet 02 Decisions
A1: Decision Register
A2: Every decision from the discovery session. Change decisions here first.
A4: ID | B4: Area | C4: Question | D4: Decision | E4: Followed recommendation | F4: Rationale and implications
A5: D01 | B5: Strategy | C5: Primary goal | D5: Build for us first, commercialise once proven | E5: Yes | F5: Proves accuracy on real money before selling it. Keeps early costs low.
A6: D02 | B6: Strategy | C6: V1 market | D6: All auction categories | E6: No | F6: Broader appeal. Requires a category agnostic engine and progressive category rules. Accuracy will vary by category and must be shown honestly.
A7: D03 | B7: Strategy | C7: Primary paying user | D7: Resellers and flippers buying for profit | E7: n/a | F7: Profit maths and bid limits are the core of the product.
A8: D04 | B8: Input | C8: Auction sources in V1 | D8: Grays, Pickles and Lloyds | E8: Yes | F8: Three structured, high volume sources. Each needs its own extractor.
A9: D05 | B9: Input | C9: Submission method | D9: URL plus PDF catalogue upload | E9: Yes | F9: PDF upload covers any auctioneer not yet supported.
A10: D06 | B10: Input | C10: Geographic scope | D10: Australia only | E10: Yes | F10: Consistent currency, GST, freight and comparables.
A11: D07 | B11: Data | C11: Comparable price gathering | D11: eBay API, web search API and retailer sites | E11: Yes | F11: Uses official APIs where possible and limits scraping risk.
A12: D08 | B12: Data | C12: Sold versus advertised weighting | D12: Sold prices weighted highest, advertised as support | E12: Yes | F12: Sold prices are evidence of what buyers actually pay.
A13: D09 | B13: Data | C13: Pricing freshness | D13: Live on each analysis, cached for seven days | E13: Yes | F13: All comparables are also stored permanently for the evidence trail, which builds a historical database at no extra cost.
A14: D10 | B14: Identification | C14: Lot identification method | D14: Text plus AI vision on lot photos | E14: Yes | F14: Model numbers are often only visible on plates in photos.
A15: D11 | B15: Identification | C15: User correction | D15: Always let the user confirm or edit the identification | E15: Yes | F15: Corrections become matching data that improves future results.
... A42: D38 | B42: Design | C42: Visual style | D42: Clean, data dense trading desk feel | E42: Yes | F42: Numbers first, calm colours, clear status signals.
A43: D39 | B43: Design | C43: Theme | D43: Light and dark mode following system | E43: Yes
A44: D40 | B44: Commercial | C44: Pricing model | D44: Subscription tiers with included credits and top up packs | E44: Yes | F44: Predictable revenue with usage based cost control.
A45: D41 | B45: Commercial | C45: Free entry | D45: Free triage with limited catalogues, pay for deep analysis | E45: Yes | F45: Users see value before paying.
A46: D42 | B46: Commercial | C46: Name | D46: Suggestions provided in this workbook | E46: Yes | F46: See tab 21.
A47: D43 | B47: Legal | C47: Positioning | D47: Decision support tool, not valuation advice | E47: Yes | F47: Clear disclaimers in the product and the terms.
A48: D44 | B48: Legal | C48: Comparable display | D48: Link, price, date and text summary. No copied images | E48: Yes | F48: Avoids copyright issues with third party photos.
A49: D45 | B49: Legal | C49: Auction data access | D49: Respect site terms, rate limit, public pages only | E49: Yes | F49: Formal partnerships considered once there is traction.
A50: D46 | B50: Delivery | C50: Builder | D50: Ashleigh with Claude Code and Codex | E50: Yes
A51: D47 | B51: Delivery | C51: Timeline | D51: Internal MVP in six to eight weeks, then iterate | E51: Yes
A52: D48 | B52: Delivery | C52: Workbook format | D52: Excel with tabs by topic | E52: n/a | F52: This file.
A53: D49 | B53: Configuration | C53: Configuration layers | D53: Platform, Organisation, User, Lot. Each lower layer overrides the one above unless locked | E53: Yes | F53: Resolution engine reads the lowest set value. See tab 27.
A54: D50 | B54: Configuration | C54: Reach of a user override | D54: That lot, in their organisation only | E54: Yes | F54: Overrides never change defaults or other lots.
A55: D51 | B55: Configuration | C55: User corrections to shared data | D55: Never applied directly. Flagged for admin review, then applied | E55: Yes | F55: Protects every other user from one person's error. See tab 31.
A56: D52 | B56: Configuration | C56: Evidence weights, match levels, confidence formula | D56: Hard coded, versioned and visible to users | E56: Yes | F56: Changed only by a versioned release with a public changelog.
A57: D53 | B57: Configuration | C57: Core maths and GST rate | D57: Hard coded, never overridable | E57: Yes | F57: A legislative GST change is handled by a code release.
A58: D54 | B58: Helper behaviour | C58: User enters own resale price | D58: Allowed. Labelled Your input with system confidence shown separately | E58: Yes | F58: The user may know more than the evidence. The system never presents their figure as its own.
A59: D55 | B59: Helper behaviour | C59: Bid above absolute maximum or break even | D59: Warn and let them proceed | E59: Yes | F59: The platform advises and never blocks a bidding decision.
A60: D56 | B60: Helper behaviour | C60: Insufficient evidence | D60: No system bid. User can enter own resale to calculate | E60: Yes
A61: D57 | B61: Helper behaviour | C61: Excluding comparables | D61: Allowed with reason recorded and valuation shown before and after | E61: Yes
A62: D58 | B62: Helper behaviour | C62: User supplied comparables | D62: Allowed. Labelled User supplied, own weight category, private to the organisation | E62: Yes | F62: Never shared with other organisations.
A63: D59 | B63: Helper behaviour | C63: Overridden value display | D63: Marker on every overridden field with one click reset to system value | E63: Yes
A64: D60 | B64: Helper behaviour | C64: Override summary | D64: Per lot summary of what has changed from the system values | E64: Yes
A65: D61 | B65: Transparency | C65: Provenance labels | D65: Every figure tagged Verified, Extracted, Estimated or Your input | E65: Yes | F65: Definitions on tab 29.
A66: D62 | B66: Transparency | C66: Negative evidence | D66: List sources searched and what was not found | E66: Yes
A67: D63 | B67: Transparency | C67: Data age | D67: Date checked on every price with a stale warning after seven days | E67: Yes
A68: D64 | B68: Transparency | C68: AI content | D68: All AI generated content labelled as AI generated | E68: Yes | F68: Identifications, match reasons and summaries.
A69: D65 | B69: Transparency | C69: Unverifiable items | D69: Fixed We cannot verify panel on every lot | E69: Yes | F69: Category specific items added to the general list.
A70: D66 | B70: Transparency | C70: Method explanation | D70: How this was calculated expander on every bid limit | E70: Yes
A71: D67 | B71: Disclaimers | C71: Terms acceptance | D71: Clickwrap at sign up, versioned, re acceptance on material change | E71: Yes | F71: Acceptance recorded with version and timestamp.
A72: D68 | B72: Disclaimers | C72: In product disclaimers | D72: Short contextual notes where the risk is, full text one tap away | E72: Yes | F72: Avoids banner blindness. Library on tab 30.
A73: D69 | B73: Disclaimers | C73: Export disclaimers | D73: Footer disclaimer, source tags and analysis date on every export | E73: Yes
A74: D70 | B74: Organisation | C74: Setting locks | D74: Org admins can lock chosen defaults for members | E74: Yes | F74: Lock types are Fixed or Floor.
A75: D71 | B75: Organisation | C75: Visibility of team overrides | D75: Visible to everyone in the organisation | E75: Yes
A76: D72 | B76: Organisation | C76: Audit history | D76: Organisation wide history of who changed what and when | E76: Yes
A77: D73 | B77: Governance | C77: New method versions | D77: Keep old results, show newer method available, user chooses to recalculate | E77: Yes | F77: Past decisions remain reproducible.
A78: D74 | B78: Governance | C78: Method changelog | D78: Public changelog of method and data source changes | E78: Yes
A79: D75 | B79: Governance | C79: Platform defaults | D79: Admin editable with change log, no deploy needed | E79: Yes | F79: Premium fallbacks, asking discounts, category lists.
A80: D76 | B80: Governance | C80: Reporting wrong data | D80: Report a problem on every lot, identification and comparable | E80: Yes | F80: Feeds the correction review queue.
A81: D77 | B81: Governance | C81: Accuracy track record | D81: Published by category once enough outcomes exist | E81: Yes | F81: Minimum sample rule on tab 31.
A82: D78 | B82: Governance | C82: Tone of warnings and disclaimers | D82: Plain, factual and neutral. States the risk and the reason | E82: Yes
A83: D79 | B83: Enrichment | C83: Fill in missing lot details | D83: Yes. Enrich lots with verifiable specifications where the item can be identified | E83: n/a | F83: Adds value beyond valuation. Spec sheet rules on tab 29.
A84: D80 | B84: Enrichment | C84: Separation of specification sources | D84: Model specifications, Observed on this lot, Auctioneer stated and Not verified are always kept separate | E84: n/a | F84: Manufacturer data describes the model, not the specific unit at auction.
A85: D81 | B85: Enrichment | C85: Unidentifiable lots | D85: No guessing. Lot marked Not identified. User can enter the model to trigger enrichment | E85: n/a | F85: User entered model is tagged Your input.
A86: D82 | B86: Enrichment | C86: When enrichment runs | D86: Deep analysis only, included in the credit | E86: Yes | F86: Enrichment also improves comparable matching, so it runs before comparable search.
A87: D83 | B87: Enrichment | C87: Conflicting information | D87: Show both values side by side and flag the conflict | E87: Yes | F87: The platform does not decide which source is right.
A88: D84 | B88: Enrichment | C88: Spec sheet delivery | D88: Section on lot detail plus downloadable PDF spec sheet | E88: Yes
A89: D85 | B89: Disclaimers | C89: Disclaimer coverage | D89: Subtle contextual notes on every screen, element, notification and export that shows an estimate or third party data | E89: n/a | F89: Coverage map and style rules on tab 30.
A90: D86 | B90: Disclaimers | C90: Recommendation wording | D90: One standard phrase: We recommend independent checks before bidding | E90: n/a | F90: Used word for word wherever a check is recommended.
A91: D87 | B91: Disclaimers | C91: Unverified details | D91: Listed as Not verified and never presented as fact, rather than left out | E91: n/a | F91: Shows the buyer what to ask the auctioneer.
A92: D88 | B92: Website | C92: Site structure | D92: Marketing site at root domain, app at app subdomain, one Next.js codebase | E92: Yes | F92: App subdomain is noindex. Shared design tokens and components.
A93: D89 | B93: Website | C93: Programmatic value guides | D93: Public price guide pages from our own aggregated data, phase 2 | E93: Yes | F93: Largest SEO lever. Publish threshold on tab 35.
A94: D90 | B94: Website | C94: AI crawler policy | D94: Allow AI search and answer crawlers, block training crawlers | E94: Yes | F94: Trade off noted on tab 36.
A95: D91 | B95: Brand | C95: Personality | D95: Sharp insider: confident, dry wit, plain speaking, on the buyer's side | E95: Yes
A96: D92 | B96: Brand | C96: Where character lives | D96: Blueprint visual details with plain trustworthy copy | E96: n/a | F96: Drawing sheet frames, title blocks, detail labels, leader dots and measurement lines. Replaces the earlier edgy direction.
A97: D93 | B97: Brand | C97: Default theme | D97: Light pages with navy blueprint headers and panels | E97: n/a | F97: Replaces dark first. A dark mode for the app is a later option.
A98: D94 | B98: Brand | C98: Colour palette | D98: Blueprint: navy, drafting white, line cyan, marker yellow and pen blue | E98: n/a | F98: Replaces lime. Yellow is kept for primary actions and the most you should bid figure, never for status.
A99: D95 | B99: Brand | C99: Typography | D99: Barlow for headings and body, Space Mono for labels and data | E99: n/a | F99: Replaces Space Grotesk, Inter and JetBrains Mono.
A100: D96 | B100: Design | C100: Visual direction | D100: Blueprint, based on engineering drawings | E100: n/a | F100: Chosen after comparing twelve options in the MaxBid design canvas.
A101: D97 | B101: Design | C101: Homepage sections | D101: Drawing sheet header with search tabs, detail cards, icon tiles, closing list with time remaining, split bar and framed navy sign up | E101: n/a | F101: Picked section by section from the Blueprint section kit.
A102: D98 | B102: Design | C102: Design sign off | D102: Blueprint approach signed off on 22 September 2026 | E102: n/a | F102: Covers homepage, catalogue results, lot detail, price guide, pricing, how we calculate and the phone lot and bid views.
A103: D99 | B103: Brand | C103: Imagery | D103: Real product UI, data visuals and bold type. No stock photos | E103: Yes
A104: D100 | B104: UX | C104: First experience | D104: Paste a catalogue URL on the homepage and see sample triage before sign up | E104: Yes | F104: Cached shared auctions keep the cost low. Rate limited.
A105: D101 | B105: UX | C105: Onboarding | D105: Three step setup then a guided first analysis | E105: Yes | F105: GST, base location, profit target.
A106: D102 | B106: UX | C106: Accessibility | D106: WCAG 2.2 AA across site and app | E106: Yes
A107: D103 | B107: Marketing | C107: Acquisition | D107: SEO, value guides and presence in reseller communities | E107: Yes
A108: D104 | B108: Marketing | C108: Signature content | D108: Weekly Auction Breakdown of top undervalued lots in a real upcoming catalogue | E108: Yes | F108: Feeds the site, email, social and communities.
A109: D105 | B109: Marketing | C109: Launch | D109: Waitlist with founding member pricing, then public launch | E109: Yes | F109: Holding page with waitlist goes live in Week 1 of the build.
A110: D106 | B110: Brand | C110: Product name | D110: MaxBid | E110: n/a | F110: Always written MaxBid. Descriptive name, so trade mark search comes before logo work.
A111: D107 | B111: Brand | C111: Domains | D111: maxbid.com.au for the marketing site, app.maxbid.com.au for the app | E111: n/a | F111: maxbid.com belongs to a US auction house, so .com.au is the primary and only domain.
A112: D108 | B112: Build | C112: Responsive approach | D112: Mobile first responsive web. Robust desktop and phone experiences from one codebase | E112: n/a | F112: Base styles written for 360px, scaled up with min width breakpoints.
A113: D109 | B113: Build | C113: Native feel on phones | D113: Installable progressive web app in V1. No native apps | E113: n/a | F113: Moved from V2. Offline watchlist and bid view, home screen install, web push.
A114: D110 | B114: Build | C114: Component library | D114: Shared UI package in a Turborepo monorepo with a Storybook catalogue | E114: Yes | F114: Nothing is built twice. Site and app use the same components.
A115: D111 | B115: Build | C115: Repository structure | D115: One monorepo with two Next.js apps (web and app) sharing packages | E115: n/a | F115: Refines D88. Separate deploys, shared code.
A116: D112 | B116: Build | C116: Page composition | D116: Thin page shells that import sections, sections built from library components | E116: n/a | F116: Pages hold routing, metadata and data loading only.
A117: D113 | B117: Build | C117: File size limit | D117: Hard cap 300 lines per file, target 150 | E117: Yes | F117: Enforced by lint in CI. Pages 80 lines, functions 80 lines.
A118: D114 | B118: Brand | C118: Writing style | D118: Complete sentences in plain everyday words, with every term and figure explained | E118: n/a | F118: Replaces the short fragment style. Twelve writing rules and examples on tab 32.
A119: D115 | B119: Build | C119: Single sources of truth | D119: Bid maths, design tokens and disclaimer text each live in one package | E119: n/a | F119: Calculator, app, exports and site can never drift apart.

Sheet 03 Users
A1: Target Users and Personas
A3: ID | B3: Priority | C3: Persona | D3: Description | E3: Main pain points | F3: What they need most | G3: Likely tier
A4: P1 | B4: Primary | C4: Part time reseller | D4: Buys a few lots a month on Grays and Pickles and resells on eBay, Facebook Marketplace and Gumtree. | E4: Overpaying, forgetting costs, time spent researching each lot. | F4: Fast triage, clear target bid, mobile bid sheet. | G4: Starter
A5: P2 | B5: Primary | C5: Full time flipper | D5: Treats auction buying as a business. Reviews many catalogues each week across categories. | E5: Volume of lots, cash flow, GST treatment, tracking actual margins. | F5: Bulk triage, cost profiles, GST cash view, outcome tracking and margin history. | G5: Pro
A6: P3 | B6: Internal | C6: Us (Ashleigh and Jason) | D6: Buying machinery, tools and general stock, including woodworking equipment for Perth Cabinet Doors. | E6: Knowing what a machine is really worth before committing. | F6: Accurate machinery matching and evidence trail. | G6: Internal
A7: P4 | B7: Secondary | C7: Dealer or liquidator | D7: Buys in volume with several staff reviewing catalogues. | E7: Consistency across buyers, approval before bidding, team visibility. | F7: Team accounts, shared watchlists, roles, exports. | G7: Dealer
A8: P5 | B8: Secondary | C8: Trade business buyer | D8: Buys equipment for own use rather than resale. | E8: Knowing a fair price compared with buying new or used elsewhere. | F8: New price and cheapest available comparison. | G8: Starter

Sheet 04 Competitors
A1: Competitor Landscape
A2: Based on the earlier research. Recheck before launch.
A3: Tool | B3: What it does | C3: Gap | D3: Relevance to us
A4: eBay Product Research | B4: Sold price history, price ranges, shipping and sell through rates for eBay listings. | C4: eBay only. No auction catalogue input, no acquisition cost or bid calculation. | D4: Data source for us rather than a direct competitor.
A5: Machinio | B5: Aggregates used machinery listings, specifications and advertised prices worldwide. | C5: Advertised prices only. No catalogue analysis or bid limits. | D5: Possible reference source for machinery comparables.
A6: EquipmentWatch | B6: Professional valuations for heavy equipment, with API access. | C6: Heavy equipment focus and professional pricing. No auction workflow. | D6: Possible paid data partner later for plant and heavy equipment.
A7: WorthPoint | B7: Realised auction results for antiques and collectibles. | C7: Collectibles only. No cost or bid engine. | D7: Possible reference for collectibles category.
A8: Manual research | B8: Google, eBay and dealer sites searched lot by lot. | C8: Slow, inconsistent, no cost modelling, no evidence record. | D8: This is the real incumbent we replace.
A10: Our position | B10: No known tool takes an Australian auction catalogue, assesses every lot, calculates full acquisition costs and tells a reseller what to bid with evidenced, confidence rated comparables.

Sheet 05 Scope
A1: Scope
A2: V1 is the internal MVP. V2 is the commercial launch. Later covers growth features.
A3: Area | B3: In V1 (internal MVP) | C3: V2 and later | D3: Excluded
A4: Catalogue input | B4: Grays, Pickles and Lloyds URLs. PDF catalogue upload. | C4: Slattery, Manheim, other auction houses. Browser extension. | D4: Facebook groups and private sales.
A5: Lot processing | B5: Extraction, triage of all lots, deep analysis of shortlisted lots. | C5: Scheduled re analysis before close. Bulk deep analysis.
A6: Identification | B6: Text and photo vision identification with user confirmation. | C6: Category specific identification rules such as VIN and rego lookup for vehicles.
A7: Comparables | B7: eBay active listings, web search results, retailer pages, auction realised results, internal outcome data. | C7: eBay Marketplace Insights sold data if approved. Paid data partners for heavy equipment. | D7: Scraping of sites whose terms prohibit it.
A8: Valuation | B8: Match levels, evidence weighting, confidence score, conservative, expected and optimistic resale. | C8: Category specific depreciation and condition models. | D8: Formal valuation certificates.
A9: Calculator | B9: Target, absolute maximum and break even bids. Profit slider. Editable cost lines. GST by profile. Cost profiles. Transport estimate. | C9: Automatic channel selling fees as an optional helper.
A10: After analysis | B10: Watchlist, closing soon alerts, outcome recording, PDF bid sheet, CSV export. | C10: Saved search alerts for new undervalued lots. Price drop alerts. Margin dashboard. | D10: Automated bidding on behalf of users.
A11: Accounts | B11: Organisations with members and roles. Email and Google sign in. | C11: Stripe billing, credits, top ups, free tier limits. | D11: Enterprise SSO.
A12: Platforms | B12: Mobile first responsive web app. Installable progressive web app with offline watchlist and bid view. | C12: Richer offline support. | D12: Native mobile apps.
A13: Geography | B13: Australia. | C13: New Zealand. | D13: Global.

Sheet 06 User Journey
A1: User Journey
A2: End to end flow for a reseller analysing one catalogue
A3: Step | B3: Stage | C3: What the user does | D3: What the system does | E3: Screen
A4: 1 | B4: Submit | C4: User pastes an auction URL or uploads a PDF and selects a cost profile. | D4: Platform detected, auction created, analysis job queued. | E4: Submit screen
A5: 2 | B5: Extract | C5: User sees a progress bar and can leave the page. | D5: Lots, photos, descriptions, locations, closing times, current bids and buyer's premium terms extracted. | E5: Analysis progress
A6: 3 | B6: Triage | C6: User receives an email and opens the ranked triage list. | D6: Quick identification, rough resale range, rough max bid and opportunity score for every lot. | E6: Triage table
A7: 4 | B7: Filter and shortlist | C7: User filters by category, value, location and closing time and ticks lots for deep analysis. Credit cost shown before confirming. | D7: Deep analysis jobs queued per lot. | E7: Triage table
A8: 5 | B8: Deep analysis | C8: User waits or returns later. Lots fill in as they complete. | D8: Vision identification, comparable search, match grading, valuation and bid calculation. | E8: Lot detail
A9: 6 | B9: Confirm identification | C9: User confirms or corrects the identified product. | D9: Correction stored. Lot revalued automatically. | E9: Lot detail
A10: 7 | B10: Review evidence | C10: User reads the match explanation and opens comparable links. | D10: Evidence shown with match level, differences, date checked and confidence. | E10: Lot detail, evidence panel
A11: 8 | B11: Adjust costs and profit | C11: User expands cost lines, edits repairs or transport, sets profit in dollars or percentage, moves the bid slider. | D11: Target, absolute maximum and break even bids recalculate instantly. | E11: Lot detail, calculator
A12: 9 | B12: Watch and export | C12: User adds lots to the watchlist and downloads the PDF bid sheet. | D12: Closing soon alerts scheduled. Bid sheet generated. | E12: Watchlist, export
A13: 10 | B13: Bid | C13: User bids on the auction site using the mobile bid view. | D13: Mobile view shows lot, target bid, absolute maximum and a clear stop line. | E13: Mobile bid view
A14: 11 | B14: Record outcome | C14: User records won or lost, final hammer price and later the actual resale price. | D14: Outcome stored as verified evidence and used to measure accuracy. | E14: Outcomes

Sheet 07 Features
A1: Feature Register
A2: Priority uses MoSCoW. Phase 1 is the internal MVP.
A3: ID | B3: Module | C3: Feature | D3: Description | E3: Priority | F3: Phase | G3: Depends on | H3: Acceptance criteria
A4: F01 | B4: Accounts | C4: Sign in | D4: Email magic link and Google sign in through Supabase Auth. | E4: Must | F4: 1 | H4: User can sign in and out on desktop and mobile.
A5: F02 | B5: Accounts | C5: Organisations | D5: Every user belongs to an organisation. Data is scoped to the organisation. | E5: Must | F5: 1 | G5: Sign in | H5: Two members of one organisation see the same analyses. Other organisations see nothing.
A6: F03 | B6: Accounts | C6: Roles | D6: Owner, admin, buyer and viewer roles. | E6: Should | F6: 1 | G6: Organisations | H6: Viewer cannot edit costs or spend credits.
A7: F04 | B7: Accounts | C7: Profile settings | D7: GST registered, base location, default cost profile, default profit target. | E7: Must | F7: 1 | G7: Organisations | H7: Changing GST registration recalculates all open lots.
A8: F05 | B8: Input | C8: URL submission | D8: Paste a Grays, Pickles or Lloyds URL. Platform detected automatically. | E8: Must | F8: 1 | H8: Unsupported URLs show a clear message and offer PDF upload.
A9: F06 | B9: Input | C9: PDF upload | D9: Upload an auction catalogue PDF for extraction. | E9: Must | F9: 1 | H9: Lots extracted from a text PDF and a scanned PDF with at least 90 percent completeness in testing.
A10: F07 | B10: Input | C10: Grays extractor | D10: Structured extraction of lots, photos, location, closing time, current bid and terms. | E10: Must | F10: 1 | G10: Extraction service | H10: All lots from a 300 lot catalogue extracted with correct lot numbers.
A11: F08 | B11: Input | C11: Pickles extractor | D11: As above for Pickles. | E11: Must | F11: 1 | G11: Extraction service | H11: As above.
A12: F09 | B12: Input | C12: Lloyds extractor | D12: As above for Lloyds. | E12: Must | F12: 1 | G12: Extraction service | H12: As above.
A13: F10 | B13: Input | C13: Buyer's premium extraction | D13: Read premium rates and GST terms from each auction's terms. Fall back to platform default. | E13: Must | F13: 1 | G13: Extractors | H13: Premium shown with its source and is editable.
A14: F11 | B14: Processing | C14: Background jobs | D14: Durable jobs with retries and fan out per lot. | E14: Must | F14: 1 | H14: A failed lot retries without restarting the catalogue.
A15: F12 | B15: Processing | C15: Progress and email | D15: Live progress bar and email when triage completes. | E15: Must | F15: 1 | G15: Background jobs | H15: Email arrives within five minutes of completion.
A16: F13 | B16: Triage | C16: Quick identification | D16: Low cost model identifies each lot from text and the primary photo. | E16: Must | F16: 1 | G16: Background jobs | H16: Category and product type assigned to every lot.
A17: F14 | B17: Triage | C17: Rough valuation | D17: One search pass returns a rough resale range and rough max bid. | E17: Must | F17: 1 | G17: Quick identification | H17: Range shown with a triage confidence label.
A18: F15 | B18: Triage | C18: Opportunity score | D18: Score from 0 to 100 ranking lots by likely margin and confidence. | E18: Must | F18: 1 | G18: Rough valuation | H18: Table sorted by score by default.
A19: F16 | B19: Triage | C19: Filters | D19: Category, value range, location and closing time. | E19: Must | F19: 1 | G19: Triage table | H19: Filters combine and persist for the session.
A20: F17 | B20: Triage | C20: Shortlist and credit preview | D20: Tick lots for deep analysis. Show credits required before confirming. | E20: Must | F20: 1 | G20: Credits ledger | H20: User cannot exceed available credits.
A21: F18 | B21: Deep analysis | C21: Vision identification | D21: Larger model reads all lot photos including data plates and labels. | E21: Must | F21: 1 | G21: Background jobs | H21: Brand and model extracted from plate photos in testing.
A22: F19 | B22: Deep analysis | C22: Identification confirmation | D22: User confirms or edits brand, model, year, specs and condition. | E22: Must | F22: 1 | G22: Vision identification | H22: Edit triggers automatic revaluation.
A23: F20 | B23: Deep analysis | C23: Comparable search | D23: Search eBay, web search API, retailer pages, auction realised results and internal data. | E23: Must | F23: 1 | G23: Data sources | H23: Each lot returns up to 15 candidate comparables.
A24: F21 | B24: Deep analysis | C24: Match grading | D24: Assign match level, reason and differences to each comparable. | E24: Must | F24: 1 | G24: Comparable search | H24: Every comparable shows a match level and a plain English reason.
A25: F22 | B25: Deep analysis | C25: New price lookup | D25: Find current or last known new retail price. | E25: Should | F25: 1 | G25: Comparable search | H25: New price shown with source and date or marked not found.
A26: F23 | B26: Deep analysis | C26: Cheapest currently advertised | D26: Lowest current advertised comparable of similar specification. | E26: Must | F26: 1 | G26: Match grading | H26: Shown with link, match level and date checked.
... A37: F34 | B37: Calculator | C37: Transport estimate | D37: Distance from base to lot location multiplied by rate per km plus base fee by size class. | E37: Should | F37: 1 | G37: Routing API | H37: Estimate shown with distance and editable.
A38: F35 | B38: After analysis | C38: Watchlist | D38: Save lots across auctions. | E38: Must | F38: 1 | H38: Watchlist shows live closing countdown.
A39: F36 | B39: After analysis | C39: Closing soon alerts | D39: Email and push alerts before a watchlisted lot closes. | E39: Should | F39: 1 | G39: Watchlist | H39: Alert timing set by the user.
A40: F37 | B40: After analysis | C40: Outcome recording | D40: Won or lost, hammer price, actual resale price and date. | E40: Must | F40: 1 | H40: Outcome feeds internal comparables.
A41: F38 | B41: After analysis | C41: PDF bid sheet | D41: One line per lot with target and absolute maximum, readable on a phone. | E41: Must | F41: 1 | G41: Bid limits | H41: Generates in under ten seconds for 50 lots.
A42: F39 | B42: After analysis | C42: CSV export | D42: Full lot data with costs and bids. | E42: Should | F42: 1 | H42: Opens cleanly in Excel.
A43: F40 | B43: Mobile | C43: Mobile bid view | D43: Large type view of watchlisted lots with target, maximum and stop line. | E43: Must | F43: 1 | G43: Watchlist | H43: Usable one handed on a phone.
A44: F41 | B44: Admin | C44: Platform admin | D44: Manage auction platforms, premium defaults, categories and extractor health. | E44: Should | F44: 1 | H44: Admin can update a platform default without a deploy.
A45: F42 | B45: Admin | C45: Cost and usage logging | D45: Record AI, search and extraction cost per job. | E45: Must | F45: 1 | G45: Background jobs | H45: Cost per catalogue visible in admin.
A46: F43 | B46: Billing | C46: Stripe subscriptions | D46: Tiers with monthly credit allowance. | E46: Must | F46: 2 | G46: Organisations | H46: Credits granted on renewal.
A47: F44 | B47: Billing | C47: Top up packs | D47: One off credit purchases. | E47: Should | F47: 2 | G47: Stripe subscriptions | H47: Credits available immediately after payment.
A48: F45 | B48: Billing | C48: Free tier limits | D48: Limited triage catalogues and starter credits. | E48: Must | F48: 2 | G48: Stripe subscriptions | H48: Limits enforced server side.
A49: F46 | B49: Growth | C49: Saved search alerts | D49: Alert when a new lot matches saved criteria with a high opportunity score. | E49: Could | F49: 3 | G49: Triage
A50: F47 | B50: Growth | C50: Margin dashboard | D50: Actual versus predicted margin over time. | E50: Could | F50: 3 | G50: Outcome recording
A51: F48 | B51: Growth | C51: Additional auction sources | D51: Slattery, Manheim and others. | E51: Should | F51: 3 | G51: Extractors
A52: F49 | B52: Growth | C52: Category rules | D52: Vehicle, machinery, tools, electronics specific valuation rules. | E52: Should | F52: 2 | G52: Valuation
A53: F50 | B53: Growth | C53: Automatic selling fees helper | D53: Optional channel fee presets. | E53: Could | F53: 3 | G53: Editable cost lines
A54: F51 | B54: Configuration | C54: Settings resolution engine | D54: Resolves each setting from Platform, Organisation, User and Lot layers with lock rules. | E54: Must | F54: 1 | G54: Organisations | H54: Unit tests cover every precedence and lock case on tab 28.
A55: F52 | B55: Configuration | C55: Organisation setting locks | D55: Admins lock chosen settings as Fixed or Floor. Enforced in the database. | E55: Must | F55: 1 | G55: Settings resolution engine | H55: A buyer cannot save a value below a Floor lock through the UI or API.
A56: F53 | B56: Configuration | C56: Override markers and reset | D56: Marker on every overridden field with one click reset to system value. | E56: Must | F56: 1 | G56: Editable cost lines | H56: Reset restores the current system value and records the change.
A57: F54 | B57: Configuration | C57: Override summary | D57: Per lot list of every field changed from the system value. | E57: Must | F57: 1 | G57: Override markers and reset | H57: Summary shows field, system value, your value, who and when.
A58: F55 | B58: Transparency | C58: Provenance tags | D58: Verified, Extracted, Estimated or Your input tag on every figure. | E58: Must | F58: 1 | H58: No figure renders without a tag.
A59: F56 | B59: Transparency | C59: AI generated labels | D59: Label on identifications, match reasons and summaries. | E59: Must | F59: 1 | H59: Label present wherever AI output is shown.
A60: F57 | B60: Transparency | C60: Searched and not found panel | D60: Lists every source queried, results found and what was not found. | E60: Must | F60: 1 | G60: Comparable search | H60: Panel shows all sources even when zero results.
A61: F58 | B61: Transparency | C61: We cannot verify panel | D61: Fixed general list plus category specific items. | E61: Must | F61: 1 | G61: Categories | H61: Present on every lot and in the bid sheet.
A62: F59 | B62: Transparency | C62: How this was calculated | D62: Expander on every bid limit showing inputs, tags, formula in words and method version. | E62: Must | F62: 1 | G62: Bid limits | H62: Figures in the expander reconcile to the bid limit.
A63: F60 | B63: Transparency | C63: Stale data warning | D63: Warning on prices checked more than seven days ago with refresh action. | E63: Must | F63: 1 | G63: Comparable search | H63: Warning appears on day eight.
A64: F61 | B64: Helper behaviour | C64: Add user comparable | D64: User adds a link or price as a private comparable. | E64: Should | F64: 1 | G64: Evidence weighting | H64: Visible only within the organisation and tagged User supplied.
A65: F62 | B65: Helper behaviour | C65: Exclude comparable with reason | D65: Exclusion requires a reason and shows valuation before and after. | E65: Must | F65: 1 | G65: Evidence weighting | H65: Before and after values shown in the override summary.
A66: F63 | B66: Helper behaviour | C66: Soft warnings | D66: Warnings for risky bids and inputs without blocking. | E66: Must | F66: 1 | G66: Disclaimer library | H66: Every situation on tab 28 produces the correct response.
A67: F64 | B67: Governance | C67: Report a problem | D67: Report action on every lot, identification and comparable. | E67: Must | F67: 1 | H67: Report reaches the admin queue with full context.
A68: F65 | B68: Governance | C68: Correction review queue | D68: Admin queue for corrections that would change shared data. | E68: Must | F68: 1 | G68: Report a problem | H68: Approved change applies to shared record with provenance recorded.
A69: F66 | B69: Governance | C69: Terms versioning and clickwrap | D69: Versioned terms with recorded acceptance and re acceptance on material change. | E69: Must | F69: 1 | G69: Sign in | H69: User cannot continue after a material change until accepted.
A70: F67 | B70: Governance | C70: Method versioning | D70: Every valuation stamped with method version. Newer method prompt with user chosen recalculation. | E70: Must | F70: 1 | G70: Valuation | H70: Old valuation remains viewable after recalculation.
A71: F68 | B71: Governance | C71: Public changelog | D71: Changelog page for method and data source changes. | E71: Should | F71: 1 | G71: Method versioning | H71: Every method release has an entry.
A72: F69 | B72: Governance | C72: Platform settings admin | D72: Admin editable platform defaults with change log. | E72: Must | F72: 1 | G72: Platform admin | H72: Every change records old value, new value, who and why.
A73: F70 | B73: Governance | C73: Organisation audit history | D73: History view of changes across the organisation. | E73: Should | F73: 1 | G73: Audit log | H73: Filter by user, lot and date.
A74: F71 | B74: Enrichment | C74: Lot enrichment | D74: Fill missing specifications from manufacturer, dealer and specification sources once the item is identified. | E74: Must | F74: 1 | G74: Vision identification | H74: Every enriched field carries a source class, provenance tag, source link and date checked.
A75: F72 | B75: Enrichment | C75: Source class separation | D75: Each field shown under Model specifications, Observed on this lot, Auctioneer stated or Not verified. | E75: Must | F75: 1 | G75: Lot enrichment | H75: No model specification is ever displayed as confirmed for the unit.
A76: F73 | B76: Enrichment | C76: Conflict flags | D76: Where sources disagree, show both values side by side with a conflict flag. | E76: Must | F76: 1 | G76: Lot enrichment | H76: Conflicts appear on lot detail, spec sheet and bid sheet.
A77: F74 | B77: Enrichment | C77: Not identified state | D77: Lots that cannot be identified show Not identified and a field for the user to enter brand and model. | E77: Must | F77: 1 | G77: Vision identification | H77: User entry triggers enrichment and revaluation.
A78: F75 | B78: Enrichment | C78: Optional equipment check | D78: List the model's known options and mark each as observed, stated, absent or not verified for this lot. | E78: Should | F78: 1 | G78: Lot enrichment | H78: Options list shown for machinery and vehicles where manufacturer data lists options.
A79: F76 | B79: Enrichment | C79: PDF spec sheet | D79: Downloadable spec sheet per lot with source classes, links, conflicts and disclaimer. | E79: Must | F79: 1 | G79: Lot enrichment | H79: Every field on the PDF matches lot detail.
... A90: F87 | B90: Growth | C90: Lifecycle email | D90: Welcome, first result, closing alerts, outcome reminder, win back. | E90: Must | F90: 2 | G90: Email | H90: Every email has an unsubscribe except transactional alerts.
A91: F88 | B91: Build | C91: Component library | D91: packages/ui with tokens, primitives and composites, catalogued in Storybook. | E91: Must | F91: 1 | H91: Every UI element used in a page exists in the library with stories.
A92: F89 | B92: Build | C92: Shared calculation package | D92: packages/calc holds the bid engine used by site, app, exports and tests. | E92: Must | F92: 1 | H92: Tab 10 cases pass as unit tests to the cent.
A93: F90 | B93: Build | C93: Shared content package | D93: packages/content holds disclaimer messages DS01 to DS35 and standard phrases. | E93: Must | F93: 1 | H93: No disclaimer text is typed directly into a page.
A94: F91 | B94: Mobile | C94: Installable web app | D94: Web app manifest, icons, standalone display and install prompt. | E94: Must | F94: 1 | H94: Installs to home screen on iOS and Android.
A95: F92 | B95: Mobile | C95: Offline bid view | D95: Service worker caches watchlist and bid view data. | E95: Must | F95: 1 | G95: Installable web app | H95: Bid view shows last synced figures with no signal and a clear last updated time.
A96: F93 | B96: Mobile | C96: Web push alerts | D96: Closing soon alerts through web push on installed app. | E96: Should | F96: 1 | G96: Installable web app | H96: Alert received on an installed iPhone and Android device.
A97: F94 | B97: Governance | C97: Accuracy page | D97: Published accuracy by category once minimum outcomes are reached. | E97: Could | F97: 2 | G97: Outcome recording | H97: Categories below the minimum show Not enough data yet.

Sheet 08 Matching Logic
A1: Matching, Evidence and Confidence Logic
A2: Starting weights. Calibrate against recorded outcomes during the MVP.
A4: Match levels
A5: Match level | B5: Definition | C5: Match weight | D5: Price adjustment | E5: Standard explanation text
A6: Exact | B6: Same brand, model and material specification. | C6: 1 | D6: None | E6: Exact match. Same brand, model and specification.
A7: Near exact | B7: Same model with a minor year or specification difference. | C7: 0.85 | D7: Small adjustment where the difference is known | E7: Same model. Differs in year or a minor option.
A8: Higher specification | B8: Comparable has greater capacity, features or performance. | C8: 0.6 | D8: Adjust price downward | E8: No exact match found. This comparable has more features, so it may overstate value.
A9: Lower specification | B9: Comparable has fewer features or lower capacity. | C9: 0.6 | D9: Adjust price upward | E9: No exact match found. This comparable has fewer features, so it may understate value.
A10: Similar alternative | B10: Different brand or model with broadly comparable capability. | C10: 0.4 | D10: Adjust by brand tier where known | E10: Different brand or model with similar capability. Treat as a guide only.
A11: Insufficient evidence | B11: No defensible comparable located. | C11: 0 | D11: Not used | E11: We could not find a reliable comparable. Enter your own resale estimate to calculate a bid.
A13: Evidence type weights
A14: Evidence type | B14: Description | C14: Evidence weight | D14: Used for
A15: Verified outcome (own organisation) | B15: Actual resale recorded by the user's organisation. | C15: 1 | D15: Resale
A16: Auction realised result | B16: Hammer price from a past Grays, Pickles or Lloyds auction, adjusted for premium. | C16: 0.95 | D16: Resale floor and auction market
A17: Marketplace sold listing | B17: Completed sale on eBay or similar, where access is available. | C17: 0.95 | D17: Resale
A18: Verified outcome (pooled, anonymised) | B18: Outcomes from other organisations, anonymised. Later phase. | C18: 0.85 | D18: Resale
A19: Used advertised listing | B19: Current asking price for a used item. | C19: 0.6 | D19: Resale ceiling. Apply asking to selling discount.
A20: User supplied comparable | B20: Link or price added by the user's organisation. Private to that organisation. | C20: 0.5 | D20: Resale, that organisation only
A21: New retail price | B21: Current or last known new price. | C21: 0 | D21: Reference only. Not used for resale.
A23: Recency decay
A24: Evidence age | B24: Recency weight
A25: 0 to 90 days | B25: 1
A26: 91 to 180 days | B26: 0.8
A27: 181 to 365 days | B27: 0.6
A28: Over 365 days | B28: 0.4
A30: Combined weight and resale scenarios
A31: Comparable weight | B31: Match weight multiplied by evidence weight multiplied by recency weight.
A32: Asking to selling discount | B32: Advertised used prices are reduced by a category default, starting at 10 percent, before weighting. Editable in admin.
A33: Conservative resale | B33: Weighted 25th percentile of adjusted comparable prices.
A34: Expected resale | B34: Weighted median of adjusted comparable prices.
A35: Optimistic resale | B35: Weighted 75th percentile of adjusted comparable prices.
A36: Minimum evidence | B36: At least three comparables with a combined weight of 1.5 or more before a scenario range is shown. Otherwise the lot is marked Low or Insufficient.
A37: Optimism flag | B37: If the user's profit target is only met on the optimistic scenario, the lot shows a visible warning.
A39: Confidence score (0 to 100)
A40: Component | B40: Calculation | C40: Weight
A41: Identification confidence | B41: Model confidence in brand and model, raised to 100 when user confirmed. | C41: 0.25
A42: Best match level | B42: Weight of the best comparable's match level multiplied by 100. | C42: 0.25
A43: Evidence volume | B43: Combined comparable weight, capped at 5, scaled to 100. | C43: 0.2
A44: Sold evidence share | B44: Share of combined weight coming from sold or realised evidence. | C44: 0.15
A45: Price agreement | B45: 100 minus coefficient of variation of adjusted prices, floored at zero. | C45: 0.15
B46: Total weight | C46: =SUM(C41:C45) -> 1
A48: Confidence label | B48: Score band
A49: High | B49: 75 and above
A50: Medium | B50: 50 to 74
A51: Low | B51: 25 to 49
A52: Insufficient | B52: Below 25, or minimum evidence not met
A54: Opportunity score for triage (0 to 100)
A55: Headroom | B55: Rough target bid minus current bid (or starting bid), divided by rough target bid.
A56: Score | B56: Headroom multiplied by triage confidence factor (High 1.0, Medium 0.75, Low 0.5), scaled to 0 to 100 and capped. Lots with a negative headroom score zero.
A57: Tie break | B57: Higher absolute dollar headroom ranks first.

Sheet 09 Cost Fields
A1: Cost Field Specification
A3: Field | B3: Source | C3: Default | D3: Editable per lot | E3: GST treatment
A4: Expected resale price | B4: System (scenario), editable | C4: Selected scenario | D4: Yes | E4: Entered GST inclusive. Registered users net off GST.
A5: Hammer price | B5: User or slider | C5: Target bid | D5: Yes | E5: GST added when the auction terms say the lot attracts GST.
A6: Buyer's premium rate | B6: Extracted from auction terms | C6: Platform default fallback | D6: Yes | E6: Usually attracts GST. Flag editable.
A7: GST on hammer | B7: Extracted | C7: From auction terms | D7: Yes | E7: Creditable for registered users.
A8: GST on premium | B8: Extracted | C8: From auction terms | D8: Yes | E8: Creditable for registered users.
A9: Transport | B9: Distance estimate | C9: Rate per km and base fee by size class from cost profile | D9: Yes | E9: Entered GST inclusive.
A10: Removal or crane | B10: User | C10: Cost profile | D10: Yes | E10: Entered GST inclusive.
A11: Repairs | B11: User | C11: Cost profile, dollars or percentage of resale | D11: Yes | E11: Entered GST inclusive.
A12: Replacement parts | B12: User | C12: Zero | D12: Yes | E12: Entered GST inclusive.
A13: Testing or certification | B13: User | C13: Cost profile | D13: Yes | E13: Entered GST inclusive.
A14: Cleaning and preparation | B14: User | C14: Cost profile | D14: Yes | E14: Entered GST inclusive.
... A19: Minimum acceptable profit | B19: User | C19: Profile default | D19: Yes | E19: Drives absolute maximum bid.

Sheet 10 Profit Calculator
A1: Profit and Bid Calculator
A2: Working model of the bid engine. Change the yellow cells. Example values are illustrative only.
A3: Settings (from user profile and lot) | E3: Bid sensitivity (slider preview)
A4: GST registered | B4: Yes | C4: Profile setting. Yes or No. | E4: % of target | F4: Hammer bid | G4: Effective acquisition cost | H4: Estimated profit | I4: Return on cost | J4: Zone
A5: GST rate | B5: 0.1 | C5: Australian GST. | E5: 0.6 | F5: =$B$46*E5 -> 4761.6075 | G5: =F5*$B$43+$B$38 -> 9120 | H5: =$B$19-G5 -> 7698.1818 | I5: =IF(G5=0,0,H5/G5) -> 0.84409888 | J5: =IF(H5>=IF($B$7="$",$B$8,$B$9*G5)-0.5,"Green",IF(H5>0,"Amber","Red")) -> Green
A6: Resale scenario | B6: Conservative | C6: Conservative, Expected or Optimistic. | E6: 0.7 | F6: =$B$46*E6 -> 5555.2087 | G6: =F6*$B$43+$B$38 -> 10044.545 | H6: =$B$19-G6 -> 6773.6364 | I6: =IF(G6=0,0,H6/G6) -> 0.67435967 | J6: =IF(H6>=IF($B$7="$",$B$8,$B$9*G6)-0.5,"Green",IF(H6>0,"Amber","Red")) -> Green
A7: Profit target type | B7: $ | C7: $ for dollars or % for return on cost. | E7: 0.8 | F7: =$B$46*E7 -> 6348.81 | G7: =F7*$B$43+$B$38 -> 10969.091 | H7: =$B$19-G7 -> 5849.0909 | I7: =IF(G7=0,0,H7/G7) -> 0.53323388 | J7: =IF(H7>=IF($B$7="$",$B$8,$B$9*G7)-0.5,"Green",IF(H7>0,"Amber","Red")) -> Green
A8: Target profit ($) | B8: 4000 | C8: Used when type is $. | E8: 0.9 | F8: =$B$46*E8 -> 7142.4112 | G8: =F8*$B$43+$B$38 -> 11893.636 | H8: =$B$19-G8 -> 4924.5455 | I8: =IF(G8=0,0,H8/G8) -> 0.41404877 | J8: =IF(H8>=IF($B$7="$",$B$8,$B$9*G8)-0.5,"Green",IF(H8>0,"Amber","Red")) -> Green
A9: Target return on cost (%) | B9: 0.25 | C9: Used when type is %. | E9: 1 | F9: =$B$46*E9 -> 7936.0125 | G9: =F9*$B$43+$B$38 -> 12818.182 | H9: =$B$19-G9 -> 4000 | I9: =IF(G9=0,0,H9/G9) -> 0.31205674 | J9: =IF(H9>=IF($B$7="$",$B$8,$B$9*G9)-0.5,"Green",IF(H9>0,"Amber","Red")) -> Green
A10: Minimum acceptable profit ($) | B10: 1500 | C10: Drives absolute maximum when type is $. | E10: 1.1 | F10: =$B$46*E10 -> 8729.6137 | G10: =F10*$B$43+$B$38 -> 13742.727 | H10: =$B$19-G10 -> 3075.4545 | I10: =IF(G10=0,0,H10/G10) -> 0.22378779 | J10: =IF(H10>=IF($B$7="$",$B$8,$B$9*G10)-0.5,"Green",IF(H10>0,"Amber","Red")) -> Amber
A11: Minimum acceptable return (%) | B11: 0.1 | C11: Drives absolute maximum when type is %. | E11: 1.2 | F11: =$B$46*E11 -> 9523.215 | G11: =F11*$B$43+$B$38 -> 14667.273 | H11: =$B$19-G11 -> 2150.9091 | I11: =IF(G11=0,0,H11/G11) -> 0.14664683 | J11: =IF(H11>=IF($B$7="$",$B$8,$B$9*G11)-0.5,"Green",IF(H11>0,"Amber","Red")) -> Amber
E12: 1.3 | F12: =$B$46*E12 -> 10316.816 | G12: =F12*$B$43+$B$38 -> 15591.818 | H12: =$B$19-G12 -> 1226.3636 | I12: =IF(G12=0,0,H12/G12) -> 0.078654306 | J12: =IF(H12>=IF($B$7="$",$B$8,$B$9*G12)-0.5,"Green",IF(H12>0,"Amber","Red")) -> Amber
A13: Resale evidence (GST inclusive prices) | E13: 1.4 | F13: =$B$46*E13 -> 11110.417 | G13: =F13*$B$43+$B$38 -> 16516.364 | H13: =$B$19-G13 -> 301.81818 | I13: =IF(G13=0,0,H13/G13) -> 0.018273888 | J13: =IF(H13>=IF($B$7="$",$B$8,$B$9*G13)-0.5,"Green",IF(H13>0,"Amber","Red")) -> Amber
A14: Conservative resale | B14: 18500 | C14: System value from tab 08 logic.
A15: Expected resale | B15: 21000 | E15: Zones: Green meets the profit target. Amber is profitable but below target. Red is break even or a loss.
A16: Optimistic resale | B16: 24000 | E16: In the app the slider is continuous. This table previews the same maths at fixed steps.
A17: Resale price includes GST | B17: Yes | C17: Yes if the price the item sells for includes GST.
A18: Selected resale price | B18: =IF(B6="Conservative",B14,IF(B6="Expected",B15,B16)) -> 18500
A19: Net resale used for profit | B19: =IF(AND(B4="Yes",B17="Yes"),B18/(1+B5),B18) -> 16818.182 | C19: Registered users remit GST on the sale, so profit uses the GST exclusive amount.
A21: Auction charges (extracted from auction terms)
A22: Buyer's premium rate | B22: 0.165 | C22: Example only. Real rate extracted per auction.
A23: GST applies to hammer price | B23: Yes
A24: GST applies to buyer's premium | B24: Yes
A26: Other costs (enter GST inclusive amounts)
A27: Transport (estimate) | B27: 750
A28: Removal or crane | B28: 0
A29: Repairs | B29: 1500
A30: Replacement parts | B30: 0
A31: Testing or certification | B31: 0
A32: Cleaning and preparation | B32: 200
A33: Storage | B33: 0
A34: Selling fees | B34: 1480
A35: Other | B35: 0
A36: Total other costs | B36: =SUM(B27:B35) -> 3930
A37: Other costs include GST | B37: Yes | C37: Registered users can claim credits on GST inclusive costs.
A38: Effective other costs | B38: =IF(AND(B4="Yes",B37="Yes"),B36/(1+B5),B36) -> 3572.7273
A40: Cost per dollar of hammer price
A41: Hammer cost factor | B41: =1+IF(B4="Yes",0,IF(B23="Yes",B5,0)) -> 1 | C41: Unregistered buyers bear the GST as a real cost.
A42: Premium cost factor | B42: =B22*(1+IF(B4="Yes",0,IF(B24="Yes",B5,0))) -> 0.165
A43: Effective cost per $1 of hammer | B43: =B41+B42 -> 1.165
A45: Bid limits
A46: Target hammer bid (Most I Would Pay) | B46: =MAX(0,IF(B7="$",(B19-B38-B8)/B43,(B19-B38*(1+B9))/(B43*(1+B9)))) -> 7936.0125 | C46: Achieves the target profit on the selected scenario.
A47: Absolute maximum hammer bid | B47: =MAX(0,IF(B7="$",(B19-B38-B10)/B43,(B19-B38*(1+B11))/(B43*(1+B11)))) -> 10081.935 | C47: Achieves the minimum acceptable profit.
A48: Break even hammer bid | B48: =MAX(0,(B19-B38)/B43) -> 11369.489 | C48: Zero profit. Never cross this.
A50: Position at the target bid
A51: Cash required to complete purchase | B51: =B46*(1+IF(B23="Yes",B5,0))+B46*B22*(1+IF(B24="Yes",B5,0))+B36 -> 14100 | C51: Includes all GST paid.
A52: Estimated GST credits | B52: =IF(B4="Yes",B46*IF(B23="Yes",B5,0)+B46*B22*IF(B24="Yes",B5,0)+IF(B37="Yes",B36-B36/(1+B5),0),0) -> 1281.8182
A53: Effective acquisition cost | B53: =B51-B52 -> 12818.182
A54: Estimated profit | B54: =B19-B53 -> 4000
A55: Return on cost | B55: =IF(B53=0,0,B54/B53) -> 0.31205674
A56: Selling fee check | B56: =IF(B34=0,"Warning: no selling fees entered","Selling fees included") -> Selling fees included
A57: Optimism check | B57: =IF(B6="Optimistic","Warning: this bid relies on the optimistic resale","Based on "&B6&" resale") -> Based on Conservative resale

Sheet 11 Data Sources
A1: Data Sources
A2: Check each source's current terms and API access before build. Cost values are estimates.
A3: Source | B3: Role | C3: Access method | D3: Data obtained | E3: Terms and risk notes | F3: Legal risk | G3: Fallback
A4: Grays | B4: Auction catalogue | C4: Managed extraction (Firecrawl or Browserbase) | D4: Lots, photos, descriptions, location, closing time, current bid, premium terms | E4: Review terms. Public pages only, rate limited. | F4: Medium | G4: PDF upload
A5: Pickles | B5: Auction catalogue | C5: Managed extraction | D5: As above | E5: As above | F5: Medium | G5: PDF upload
A6: Lloyds | B6: Auction catalogue | C6: Managed extraction | D6: As above | E6: As above | F6: Medium | G6: PDF upload
A7: Auction PDF catalogues | B7: Auction catalogue | C7: PDF text extraction with OCR fallback, then Claude structuring | D7: Lots and descriptions. Photos where embedded. | E7: User supplied. Low risk. | F7: Low | G7: Manual lot entry
A8: Past auction results | B8: Sold evidence | C8: Managed extraction of published results pages where available | D8: Realised hammer prices | E8: Review terms per site. | F8: Medium | G8: Internal outcomes
A9: eBay Browse API | B9: Advertised evidence | C9: Official API | D9: Active listings, price, condition, location | E9: Official API terms. Low risk. | F9: Low | G9: Web search API
A10: eBay Marketplace Insights API | B10: Sold evidence | C10: Official API, restricted access | D10: Sold prices | E10: Requires eBay approval. Apply early. | F10: Low | G10: Auction results and internal outcomes
A11: Web search API (Brave or SerpAPI) | B11: Discovery | C11: Official API | D11: Retailer and dealer pages, new prices, specification pages | E11: Official API terms. | F11: Low | G11: Alternative search provider
A12: Retailer and dealer pages | B12: Advertised and new price evidence | C12: Fetch pages found through search, extract price and specs with Claude | D12: Advertised price, new price, specifications | E12: Respect robots and terms. Cache seven days. | F12: Medium | G12: Search snippet only, lower weight
A13: Manufacturer sites | B13: Specification and new price | C13: Fetch via search results | D13: Specs, RRP, model history | E13: Low | F13: Low | G13: Mark new price not found
A14: Internal outcomes | B14: Sold evidence | C14: Our own database | D14: Actual hammer and resale prices recorded by users | E14: Our data. Privacy policy must cover use. | F14: Low | G14: None needed
... A16: Routing API (Google Routes or Mapbox) | B16: Transport | C16: Official API | D16: Road distance between user base and lot location | E16: Official API terms. | F16: Low | G16: Straight line distance with uplift factor

Sheet 12 Pipeline
A1: Processing Pipeline
A2: Each stage is an Inngest or Trigger.dev function. Lots fan out as independent steps.
A3: Stage | B3: Name | C3: Trigger | D3: Work performed | E3: AI usage | F3: Writes to | G3: Typical duration
A4: S1 | B4: Ingest | C4: User submits URL or PDF | D4: Detect platform, create auction and analysis records, check triage allowance | E4: None | F4: auction, analysis | G4: Seconds
A5: S2 | B5: Extract | C5: S1 complete | D5: Fetch catalogue pages or parse PDF. Paginate. Store raw payload. | E5: Claude for PDF structuring only | F5: raw_extract | G5: 1 to 5 min
A6: S3 | B6: Normalise | C6: S2 complete | D6: Map to lot records. Download primary photo references. Parse premium and GST terms. | E6: Claude for premium terms parsing | F6: lot, lot_image, premium rule | G6: Under 1 min
A7: S4 | B7: Triage identify | C7: Per lot | D7: Classify category and product type from text and primary photo. | E7: Small model (Claude Haiku class) | F7: lot_identification (triage) | G7: Parallel
A8: S5 | B8: Triage value | C8: Per lot | D8: One search pass plus internal history lookup. Rough resale range. | E8: Small model to read results | F8: triage_valuation | G8: Parallel
A9: S6 | B9: Rank and notify | C9: All lots complete | D9: Rough max bid with the selected cost profile, opportunity score, email user. | E9: None | F9: Updated lots, notification | G9: Seconds
A10: S7 | B10: Shortlist | C10: User confirms selection | D10: Reserve credits in ledger, queue deep jobs. | E10: None | F10: credit_ledger entries | G10: Seconds
A11: S8 | B11: Deep identify | C11: Per shortlisted lot | D11: Read all photos including plates. Extract brand, model, year, specs, condition notes. | E11: Large model (Claude Sonnet class) with vision | F11: lot_identification (deep) | G11: Parallel
A12: S8A | B12: Enrich | C12: S8 complete and item identified | D12: Search manufacturer, dealer and specification sources for the identified model. Build field list with source class. Detect conflicts with the auctioneer description and photos. | E12: Large model to read and reconcile specification pages | F12: lot_spec_fields, product_spec_sources | G12: Parallel
A13: S9 | B13: Comparable search | C13: S8A complete | D13: Query eBay, search API, internal history and auction results. Fetch candidate pages. | E13: Small model to generate queries | F13: comparable, comparable_snapshot | G13: Parallel
A14: S10 | B14: Match grading | C14: S9 complete | D14: Assign match level, reason, differences and price adjustment to each comparable. | E14: Large model | F14: lot_comparable | G14: Parallel
... A19: S15 | B19: Closing alerts | C19: Scheduled | D19: Find watchlisted lots closing within the user's window and send alerts. | E19: None | F19: notification | G19: Every 5 min
A21: Design rules | B21: AI is used for reading, identifying and grading. All money maths is deterministic code, never AI. Every AI output is stored with the model name, prompt version and cost so results are reproducible and auditable.

Sheet 13 Database
A1: Database Schema (Supabase Postgres)
A2: All tables have created_at and updated_at timestamptz unless noted. Organisation scoped tables carry org_id for RLS.
A3: Table | B3: Purpose | C3: Column | D3: Type | E3: Nullable | F3: Keys | G3: Notes
A4: organisations | B4: Tenant. Everything belongs to an organisation. | C4: id | D4: uuid | E4: No | F4: PK | G4: Default gen_random_uuid()
A5: organisations | C5: name | D5: text | E5: No
A6: organisations | C6: plan | D6: text | E6: No | G6: free, starter, pro, dealer, internal
A7: organisations | C7: stripe_customer_id | D7: text | E7: Yes | G7: Phase 2
A8: organisations | C8: gst_registered | D8: boolean | E8: No | G8: Organisation level default
A9: organisations | C9: base_address | D9: text | E9: Yes | G9: Used for transport estimates
A10: organisations | C10: base_lat | D10: numeric | E10: Yes
A11: organisations | C11: base_lng | D11: numeric | E11: Yes
A12: profiles | B12: One row per auth user. | C12: id | D12: uuid | E12: No | F12: PK, FK auth.users
A13: profiles | C13: full_name | D13: text | E13: Yes
A14: profiles | C14: default_org_id | D14: uuid | E14: Yes | F14: FK organisations
A15: profiles | C15: alert_lead_minutes | D15: integer | E15: No | G15: Default 30
A16: organisation_members | B16: Membership and role. | C16: org_id | D16: uuid | E16: No | F16: PK, FK organisations
A17: organisation_members | C17: user_id | D17: uuid | E17: No | F17: PK, FK profiles
A18: organisation_members | C18: role | D18: text | E18: No | G18: owner, admin, buyer, viewer
A19: cost_profiles | B19: Saved default cost assumptions. | C19: id | D19: uuid | E19: No | F19: PK
A20: cost_profiles | C20: org_id | D20: uuid | E20: No | F20: FK organisations
A21: cost_profiles | C21: name | D21: text | E21: No | G21: For example Machinery
A22: cost_profiles | C22: is_default | D22: boolean | E22: No
A23: cost_profiles | C23: profit_mode | D23: text | E23: No | G23: dollars or percent
A24: cost_profiles | C24: target_profit_amount | D24: numeric(12,2) | E24: Yes
A25: cost_profiles | C25: target_return_pct | D25: numeric(6,4) | E25: Yes
A26: cost_profiles | C26: min_profit_amount | D26: numeric(12,2) | E26: Yes
A27: cost_profiles | C27: min_return_pct | D27: numeric(6,4) | E27: Yes
A28: cost_profiles | C28: transport_base_fee | D28: numeric(12,2) | E28: Yes
A29: cost_profiles | C29: transport_rate_per_km | D29: numeric(8,2) | E29: Yes
A30: cost_profiles | C30: repair_mode | D30: text | E30: No | G30: dollars or percent_of_resale
A31: cost_profiles | C31: repair_value | D31: numeric(12,4) | E31: Yes
A32: cost_profiles | C32: defaults | D32: jsonb | E32: No | G32: Other line item defaults keyed by cost field
A33: categories | B33: Category tree and category specific rules. | C33: id | D33: uuid | E33: No | F33: PK
A34: categories | C34: parent_id | D34: uuid | E34: Yes | F34: FK categories
A35: categories | C35: name | D35: text | E35: No
A36: categories | C36: asking_discount_pct | D36: numeric(6,4) | E36: No | G36: Default 0.10
A37: categories | C37: valuation_rules | D37: jsonb | E37: No | G37: Category specific rules added progressively
A38: auction_platforms | B38: Supported auction houses. | C38: id | D38: uuid | E38: No | F38: PK
A39: auction_platforms | C39: slug | D39: text | E39: No | F39: Unique | G39: grays, pickles, lloyds, pdf
A40: auction_platforms | C40: name | D40: text | E40: No
A41: auction_platforms | C41: url_patterns | D41: text[] | E41: No | G41: For platform detection
A42: auction_platforms | C42: default_premium_pct | D42: numeric(6,4) | E42: Yes | G42: Fallback only
A43: auction_platforms | C43: default_premium_gst | D43: boolean | E43: No
A44: auction_platforms | C44: extractor_version | D44: text | E44: No
A45: auction_platforms | C45: is_active | D45: boolean | E45: No
A46: auctions | B46: One auction event. Shared across organisations to avoid duplicate extraction. | C46: id | D46: uuid | E46: No | F46: PK
A47: auctions | C47: platform_id | D47: uuid | E47: No | F47: FK auction_platforms
A48: auctions | C48: source_url | D48: text | E48: Yes | F48: Unique with platform | G48: Null for PDF uploads
A49: auctions | C49: title | D49: text | E49: Yes
A50: auctions | C50: closes_at | D50: timestamptz | E50: Yes
A51: auctions | C51: location_text | D51: text | E51: Yes
A52: auctions | C52: premium_pct | D52: numeric(6,4) | E52: Yes | G52: Extracted from terms
A53: auctions | C53: premium_gst | D53: boolean | E53: Yes
A54: auctions | C54: premium_source | D54: text | E54: No | G54: extracted, platform_default, user
A55: auctions | C55: raw_terms | D55: text | E55: Yes
A56: auctions | C56: extracted_at | D56: timestamptz | E56: Yes
A57: analyses | B57: An organisation's analysis of an auction. | C57: id | D57: uuid | E57: No | F57: PK
A58: analyses | C58: org_id | D58: uuid | E58: No | F58: FK organisations
A59: analyses | C59: auction_id | D59: uuid | E59: No | F59: FK auctions
A60: analyses | C60: created_by | D60: uuid | E60: No | F60: FK profiles
A61: analyses | C61: cost_profile_id | D61: uuid | E61: No | F61: FK cost_profiles
A62: analyses | C62: source_type | D62: text | E62: No | G62: url or pdf
A63: analyses | C63: pdf_path | D63: text | E63: Yes | G63: Supabase Storage path
A64: analyses | C64: status | D64: text | E64: No | G64: queued, extracting, triaging, triaged, deep_running, complete, failed
A65: analyses | C65: progress_pct | D65: integer | E65: No
A66: analyses | C66: premium_override_pct | D66: numeric(6,4) | E66: Yes | G66: User edit
A67: lots | B67: Lots within an auction. Shared, not organisation scoped. | C67: id | D67: uuid | E67: No | F67: PK
A68: lots | C68: auction_id | D68: uuid | E68: No | F68: FK auctions
A69: lots | C69: lot_number | D69: text | E69: No | F69: Unique with auction
A70: lots | C70: title | D70: text | E70: No
A71: lots | C71: description | D71: text | E71: Yes
A72: lots | C72: source_url | D72: text | E72: Yes
A73: lots | C73: location_text | D73: text | E73: Yes
A74: lots | C74: lat | D74: numeric | E74: Yes
A75: lots | C75: lng | D75: numeric | E75: Yes
A76: lots | C76: closes_at | D76: timestamptz | E76: Yes
A77: lots | C77: current_bid | D77: numeric(12,2) | E77: Yes | G77: Updated on refresh
A78: lots | C78: gst_on_hammer | D78: boolean | E78: Yes
A79: lots | C79: raw | D79: jsonb | E79: No | G79: Original extracted payload
A80: lot_images | B80: Image references for vision. Not displayed to other users as comparables. | C80: id | D80: uuid | E80: No | F80: PK
A81: lot_images | C81: lot_id | D81: uuid | E81: No | F81: FK lots
A82: lot_images | C82: url | D82: text | E82: No
A83: lot_images | C83: position | D83: integer | E83: No
A84: products | B84: Canonical product catalogue built over time. | C84: id | D84: uuid | E84: No | F84: PK
A85: products | C85: category_id | D85: uuid | E85: Yes | F85: FK categories
A86: products | C86: brand | D86: text | E86: Yes
A87: products | C87: model | D87: text | E87: Yes
A88: products | C88: variant | D88: text | E88: Yes
A89: products | C89: specs | D89: jsonb | E89: No
A90: products | C90: new_price | D90: numeric(12,2) | E90: Yes
A91: products | C91: new_price_source_url | D91: text | E91: Yes
A92: products | C92: new_price_checked_at | D92: timestamptz | E92: Yes
A93: products | C93: embedding | D93: vector(1536) | E93: Yes | G93: pgvector for similarity matching
A94: product_aliases | B94: Alternative names and model codes. | C94: id | D94: uuid | E94: No | F94: PK
A95: product_aliases | C95: product_id | D95: uuid | E95: No | F95: FK products
A96: product_aliases | C96: alias | D96: text | E96: No
A97: lot_identifications | B97: Versioned identification of a lot for an analysis. | C97: id | D97: uuid | E97: No | F97: PK
A98: lot_identifications | C98: analysis_id | D98: uuid | E98: No | F98: FK analyses
A99: lot_identifications | C99: lot_id | D99: uuid | E99: No | F99: FK lots
A100: lot_identifications | C100: stage | D100: text | E100: No | G100: triage, deep, user
...

Sheet 14 Security
A1: Security and Row Level Security
A3: Area | B3: Applies to | C3: Rule
A4: Organisation scoped tables | B4: analyses, analysis_lots, lot_identifications, valuations, lot_costs, outcomes, cost_profiles, notifications, exports, credit_ledger | C4: Select, insert and update allowed where org_id is in the user's memberships. Helper function is_org_member(org_id).
A5: Shared tables | B5: auctions, lots, lot_images, products, product_aliases, comparables, comparable_snapshots, categories, auction_platforms | C5: Read for any signed in user. Write only by the service role through background jobs.
A6: Match table | B6: lot_comparables | C6: Readable when the linked identification belongs to the user's organisation. Written by service role. Users may update excluded_by_user only.
A7: Roles | B7: owner, admin, buyer, viewer | C7: Viewer read only. Buyer can edit costs, confirm identifications and spend credits. Admin manages members and profiles. Owner manages billing.
A8: Credits | B8: credit_ledger | C8: Insert only through a security definer function that checks balance atomically. No direct client writes.
A9: Service role | B9: Inngest or Trigger.dev functions | C9: Service key held only in server environment variables. Never sent to the browser.
A10: Storage | B10: PDF uploads and exports buckets | C10: Private buckets. Paths prefixed by org_id. Signed URLs with short expiry.
A11: Secrets | B11: API keys for Claude, search, extraction, routing, Stripe | C11: Stored in Vercel and job runner environments. Rotated on staff change.
A12: Privacy | B12: Outcomes and user data | C12: Pooled use of outcomes only with explicit consent flag. Privacy policy aligned to the Australian Privacy Principles.
A13: Abuse controls | B13: Submission endpoints | C13: Rate limit per organisation. Maximum lots per catalogue per tier. Bot protection on sign up.
A14: Platform settings | B14: platform_settings, platform_setting_changes, method_versions | C14: Read for signed in users. Write only by platform admins, with the change log written in the same transaction.
... A18: Terms | B18: terms_acceptances | C18: Insert own acceptance only. Middleware blocks app access when a material version is unaccepted.

Sheet 15 Tech Stack
A1: Technology Stack
A2: Confirm current pricing and limits for each service before build.
A3: Layer | B3: Choice | C3: Why | D3: Alternative
A4: Frontend | B4: Next.js App Router, TypeScript, Tailwind CSS, shadcn/ui | C4: Matches existing HSES Online skills | D4: Remix
A5: Tables | B5: TanStack Table | C5: Dense, sortable, filterable lot tables | D5: AG Grid
A6: Hosting | B6: Vercel | C6: Native Next.js hosting | D6: Netlify
A7: Database and auth | B7: Supabase Postgres, Auth, Storage, pgvector | C7: RLS for multi tenancy, vector search for product matching | D7: Neon plus Clerk
A8: Background jobs | B8: Inngest or Trigger.dev | C8: Durable steps, retries, fan out, schedules | D8: Supabase Queues
A9: AI | B9: Claude API. Haiku class for triage, Sonnet class for deep analysis and vision | C9: Strong vision and structured output | D9: Model agnostic layer later
A10: Page extraction | B10: Firecrawl or Browserbase | C10: Rendered pages without running our own browsers | D10: Self hosted Playwright
A11: PDF parsing | B11: Text extraction with OCR fallback, then Claude structuring | C11: Handles scanned catalogues | D11: Claude PDF input directly
A12: Web search | B12: Brave Search API or SerpAPI | C12: Predictable structured results | D12: Claude web search tool
A13: Marketplace data | B13: eBay Browse API, Marketplace Insights if approved | C13: Official access | D13: Search API results
A14: Routing | B14: Google Routes API or Mapbox | C14: Road distance for transport estimates | D14: OpenRouteService
... A18: Payments | B18: Stripe Billing (phase 2) | C18: Subscriptions, credits and top ups | D18: Paddle
A19: Monitoring | B19: Sentry | C19: Error tracking across app and jobs
A20: Analytics | B20: PostHog | C20: Product analytics and feature flags | D20: Plausible
A21: Development | B21: Claude Code and Codex, GitHub, GitHub Actions | C21: Existing workflow
A22: Testing | B22: Vitest for calculator maths, Playwright for end to end | C22: Bid maths must be tested to the cent
A23: Fonts | B23: next/font self hosting Barlow and Space Mono | C23: No layout shift, no third party font requests
A24: Monorepo | B24: Turborepo with pnpm workspaces | C24: Shared packages, cached builds, one repository | D24: Nx
A25: Component catalogue | B25: Storybook with the test runner and a11y addon | C25: Build and review components in isolation before pages | D25: Ladle
A26: Visual regression | B26: Chromatic, or Playwright screenshot tests | C26: Catches unintended visual changes per component | D26: Decide in O16
A27: Code size limits | B27: ESLint max-lines and max-lines-per-function rules | C27: Keeps every file small and editable
A28: Bundle budgets | B28: size-limit and Next.js bundle analyzer in CI | C28: Fails the build when a route grows past budget
A29: Installable web app | B29: Web app manifest with Serwist service worker | C29: Offline bid view and home screen install
A30: Agent rules | B30: CLAUDE.md and AGENTS.md at repo root | C30: Claude Code and Codex follow the same architecture rules
A31: Styling | B31: Tailwind CSS v4 with CSS variable tokens and restyled shadcn/ui | C31: One token set drives site and app, light and dark
A32: Marketing content | B32: MDX in the repo for static pages, database driven pages for guides and breakdowns | C32: Version controlled copy, programmatic scale | D32: Sanity or Payload CMS later
A33: Social images | B33: Next.js ImageResponse (Open Graph image generation) | C33: Branded share cards per page
A34: Search tooling | B34: Google Search Console, Bing Webmaster Tools, IndexNow | C34: Indexing and monitoring. Bing feeds several AI answer engines
A35: Accessibility testing | B35: axe core in Playwright runs and manual screen reader checks | C35: WCAG 2.2 AA enforced in CI

Sheet 16 Screens
A1: Screen Inventory
A3: ID | B3: Screen | C3: Purpose | D3: Key components | E3: Device
A4: SC01 | B4: Sign in | C4: Access | D4: Magic link, Google sign in | E4: Both
A5: SC02 | B5: Dashboard | C5: Recent analyses, watchlist closing soon, credit balance | D5: Analysis cards, closing countdown list, credit meter | E5: Desktop first
A6: SC03 | B6: New analysis | C6: Submit URL or PDF and choose cost profile | D6: URL field with platform detection, PDF drop zone, profile selector, triage allowance note | E6: Both
A7: SC04 | B7: Analysis progress | C7: Show extraction and triage progress | D7: Stage stepper, progress bar, leave page notice | E7: Both
A8: SC05 | B8: Triage table | C8: Rank and shortlist lots | D8: Dense table, opportunity score, rough range, rough max bid, filters, checkbox shortlist, credit preview bar | E8: Desktop first
A9: SC06 | B9: Lot detail | C9: Deep analysis result for one lot | D9: Photo strip, identification card with confirm and edit, valuation band, confidence badge, bid limits, calculator | E9: Desktop first
A10: SC06A | B10: Spec sheet section | C10: Enriched specifications for the lot | D10: Four source class groups, optional equipment checklist, conflict flags, source links, Report a problem, download PDF | E10: Desktop first
A11: SC07 | B11: Evidence panel | C11: Show comparables | D11: Comparable rows with match level badge, reason, differences, price, date checked, link, exclude toggle | E11: Desktop first
A12: SC08 | B12: Calculator panel | C12: Costs and profit | D12: Collapsed cost summary with expand, profit mode toggle, bid slider with green, amber and red zones, cash required and effective cost | E12: Both
A13: SC09 | B13: Watchlist | C13: Track lots across auctions | D13: List with countdown, target and absolute maximum, alert settings | E13: Both
A14: SC10 | B14: Mobile bid view | C14: Use while bidding | D14: One lot per card, very large target and maximum figures, stop line, swipe between lots | E14: Mobile
... A21: SC17 | B21: Try before sign up result | C21: Sample triage for anonymous visitors | D21: Top lots from a cached triage, blurred remainder, sign up call to action, DS21 note | E21: Both

Sheet 17 Design System
A1: Design System
A2: Blueprint direction. Light pages, navy panels, data dense and precise. Signed off 22 September 2026.
A3: Principles | B3: Numbers first. Calm neutral surfaces. Colour used only for meaning: profit zones, confidence and match levels. Every figure shows its basis on hover or tap.
A4: Typography | B4: Barlow 700 to 800 for headings and bid figures. Barlow 400 to 600 for body and interface text, with tabular figures on all numbers. Space Mono for lot numbers, model codes and uppercase data labels. Base size 15px on desktop tables, 16px on mobile, 48px or larger for bid figures in the phone bid view. Full brand system on tab 33.
A5: Density | B5: Table rows 36px on desktop with a comfortable option at 44px. Sticky table header and first column.
A6: Numbers | B6: Whole dollars in tables, cents only in the calculator detail. Negative values in red with a minus sign replaced by parentheses in exports.
A7: Accessibility | B7: WCAG 2.2 AA contrast on light pages and navy panels. Status never shown by colour alone: every zone and badge carries a text label.
A9: Token | B9: Use | C9: Light pages | D9: On navy panels | E9: Notes
A10: background | B10: Page background | C10: #F4F7FA | E10: Drafting white
A11: surface | B11: Cards, tables and search panel | C11: #FFFFFF | D11: #0E2A47 | E11: Navy is the panel colour for headers, bid limits and sign up
A12: surface_muted | B12: Table headers on light, photo placeholders, chips | C12: #E6EDF4 | D12: rgba(255,255,255,0.14)
A13: border | B13: Hairlines and dividers | C13: #C9D6E3 | D13: #7FC8F8 at 50 percent | E13: Double inset frame lines on navy panels
A14: ink | B14: Primary text | C14: #0E1B2B | D14: #FFFFFF
A15: ink_muted | B15: Secondary text and notes | C15: #4A5A6D | D15: #B7CDE3 | E15: Disclaimer notes use this
A16: accent | B16: Marker yellow. Primary buttons, stop line, most you should bid | C16: #FFD23F fill with #0E1B2B text | D16: #FFD23F fill with #0E1B2B text | E16: Never used for status or as text colour
A17: line | B17: Drafting lines and labels on navy | D17: #7FC8F8 | E17: Title blocks, mono labels, frame lines
A18: link | B18: Links, icons, index numbers | C18: #1B6FD1 | D18: #7FC8F8
A19: zone_green | B19: Meets profit target | C19: #1E7A52 | D19: #6EE7B7 | E19: Label: On target
A20: zone_amber | B20: Profitable, below target | C20: #B45309 | D20: #FBBF24 | E20: Label: Below target. Distinct from marker yellow
A21: zone_red | B21: Break even or loss | C21: #B91C1C | D21: #F87171 | E21: Label: Loss risk
A22: tag_verified | B22: Verified tag | C22: #1E7A52 fill, white text
A23: tag_extracted | B23: Extracted tag | C23: #E6EDF4 fill, ink text
A24: tag_estimated | B24: Estimated tag | C24: #FFF4CC fill, ink text
A25: tag_your_input | B25: Your input tag | C25: #1B6FD1 fill, white text
A26: confidence_high | B26: High confidence | C26: #1E7A52 | D26: #6EE7B7
A27: confidence_medium | B27: Medium confidence | C27: #0E1B2B | D27: #FFFFFF
A28: confidence_low | B28: Low confidence | C28: #B45309 | D28: #FBBF24
A29: confidence_insufficient | B29: Not enough evidence | C29: #6B7280 | D29: #9CA3AF
A31: Component | B31: Specification
A32: Match level badge | B32: Pill with icon and text. Exact and Near exact solid. Spec and alternative outlined. Insufficient grey.
A33: Confidence badge | B33: Pill with label and score on hover.
A34: Bid slider | B34: Track coloured by zone with markers at target, absolute maximum and break even. Live readout of profit and return.
A35: Cost summary | B35: One line total with a chevron to expand line items. Flag icon when selling fees are blank.
A36: Evidence row | B36: Source, price, date checked, match badge, one line reason, expand for differences, external link icon.
A37: Stop line | B37: Marker yellow bar at the break even price, with a yellow Stop bidding panel in the phone bid view.

Sheet 18 Commercial
A1: Commercial Model
A2: Indicative pricing in AUD excluding GST. Validate after the internal MVP. One credit equals one deep analysed lot.
A3: Tier | B3: Monthly price ($) | C3: Triage catalogues per month | D3: Deep credits per month | E3: Seats | F3: Includes | G3: Target persona
A4: Free | B4: 0 | C4: 1 | D4: 5 | E4: 1 | F4: Triage, limited deep analysis, watchlist | G4: Entry point
A5: Starter | B5: 79 | C5: 5 | D5: 40 | E5: 1 | F5: All V1 features, PDF bid sheet, alerts | G5: Part time reseller
A6: Pro | B6: 199 | C6: 12 | D6: 100 | E6: 3 | F6: Everything in Starter, CSV export, outcome analytics | G6: Full time flipper
A7: Dealer | B7: 699 | C7: 40 | D7: 400 | E7: 10 | F7: Everything in Pro, team roles, priority processing | G7: Dealers and liquidators
A9: Top up pack | B9: Credits | C9: Price ($) | D9: Price per credit
A10: Top up small | B10: 25 | C10: 39 | D10: =C10/B10 -> 1.56
A11: Top up large | B11: 100 | C11: 129 | D11: =C11/B11 -> 1.29
A13: Credit rules | B13: Credits reserved when deep analysis starts and settled on completion. Failed lots are refunded automatically. Revaluation after a correction is free when cached comparables are reused and costs one credit when a new search is needed.
A14: Rollover | B14: Unused plan credits roll over for one month. Top up credits last twelve months.
A15: Annual plans | B15: Two months free on annual billing.
A16: Pricing rule | B16: Price per credit must stay well above the deep analysis cost per lot on tab 19. Every tier should hold at least 30 percent gross margin at full usage. First draft prices failed this test and were revised.

Sheet 19 Unit Economics
A1: Unit Economics
A2: All cost inputs are estimates in AUD. Replace with logged actuals from ai_runs and usage_events during the MVP.
A3: Inputs
A4: Lots per catalogue | B4: 300 | C4: Typical large Grays catalogue.
A5: Extraction cost per catalogue | B5: 1.5 | C5: Estimate. Managed extraction service.
A6: Triage cost per lot | B6: 0.02 | C6: Estimate. Small model plus one search call.
A7: Deep analysis cost per lot | B7: 0.6 | C7: Estimate. Vision, several searches, page fetches and grading.
A8: Shortlist rate | B8: 0.1 | C8: Share of lots users send to deep analysis.
A9: Infrastructure overhead per catalogue | B9: 0.5 | C9: Estimate. Hosting, storage, email, jobs.
A10: Organisations sharing each catalogue | B10: 2 | C10: Extraction and triage identification run once per auction and are shared. Set to 1 for the worst case.
A11: Cost per catalogue
A12: Triage cost (shared) | B12: =B4*B6/B10 -> 3
A13: Lots deep analysed | B13: =ROUND(B4*B8,0) -> 30
A14: Deep analysis cost | B14: =B13*B7 -> 18
A15: Total cost per catalogue | B15: =B5/B10+B12+B14+B9 -> 22.25
A16: Cost per deep credit (deep cost only) | B16: =B7 -> 0.6
A18: Tier margin at full usage
A19: Tier | B19: Price ($) | C19: Triage cost ($) | D19: Deep cost ($) | E19: Total cost ($) | F19: Gross margin
A20: ='18 Commercial'!A4 -> Free | B20: ='18 Commercial'!B4 -> 0 | C20: ='18 Commercial'!C4*(($B$5+$B$4*$B$6)/$B$10+$B$9) -> 4.25 | D20: ='18 Commercial'!D4*$B$7 -> 3 | E20: =C20+D20 -> 7.25 | F20: =IF(B20=0,"Acquisition cost",(B20-E20)/B20) -> Acquisition cost
A21: ='18 Commercial'!A5 -> Starter | B21: ='18 Commercial'!B5 -> 79 | C21: ='18 Commercial'!C5*(($B$5+$B$4*$B$6)/$B$10+$B$9) -> 21.25 | D21: ='18 Commercial'!D5*$B$7 -> 24 | E21: =C21+D21 -> 45.25 | F21: =IF(B21=0,"Acquisition cost",(B21-E21)/B21) -> 0.42721519
A22: ='18 Commercial'!A6 -> Pro | B22: ='18 Commercial'!B6 -> 199 | C22: ='18 Commercial'!C6*(($B$5+$B$4*$B$6)/$B$10+$B$9) -> 51 | D22: ='18 Commercial'!D6*$B$7 -> 60 | E22: =C22+D22 -> 111 | F22: =IF(B22=0,"Acquisition cost",(B22-E22)/B22) -> 0.44221106
A23: ='18 Commercial'!A7 -> Dealer | B23: ='18 Commercial'!B7 -> 699 | C23: ='18 Commercial'!C7*(($B$5+$B$4*$B$6)/$B$10+$B$9) -> 170 | D23: ='18 Commercial'!D7*$B$7 -> 240 | E23: =C23+D23 -> 410 | F23: =IF(B23=0,"Acquisition cost",(B23-E23)/B23) -> 0.41344778
A25: Full usage is the worst case. Most subscribers use well below their allowance. The free tier is a marketing cost and shows as a negative margin by design.

Sheet 20 Legal
A1: Legal and Compliance
A2: Obtain legal review of terms and disclaimers before public launch.
A3: Area | B3: Requirement | C3: Where it applies
A4: Positioning | B4: Decision support tool. Not valuation advice, financial advice or a guarantee of resale value. | C4: Terms of use, onboarding, lot detail footer, bid sheet footer
A5: Standard disclaimer | B5: Values are estimates based on publicly available information at the date checked. Inspect items and verify condition before bidding. You are responsible for your bidding decisions. | C5: Every lot and every export
A6: Confidence disclosure | B6: Match level and confidence shown next to every value. Insufficient evidence lots show no system bid. | C6: Lot detail, triage table
A7: Australian Consumer Law | B7: Avoid misleading claims in marketing such as guaranteed profit or accurate valuations. | C7: Website, ads, emails
A8: GST | B8: Calculator explains GST treatment in plain terms and states it is not tax advice. | C8: Calculator panel, help page
A9: Privacy | B9: Privacy policy aligned to the Australian Privacy Principles. Explicit consent before pooled use of outcomes. | C9: Sign up, settings
A10: Third party content | B10: Show link, price, date and our own text summary. Do not copy or display third party photos as comparables. | C10: Evidence panel
A11: Auction data access | B11: Respect each site's terms and robots rules. Public pages only. Rate limited. No login bypass. Stop and seek permission where terms prohibit automated access. | C11: Extractors
A12: API terms | B12: Comply with eBay, search API and routing API terms including attribution and caching limits. | C12: Data layer
A13: Automated bidding | B13: Not offered. Users bid themselves on the auction site. | C13: Scope

Sheet 21 Naming
A1: Name Candidates
A2: Selected: MaxBid at maxbid.com.au. Remaining candidates kept as fallbacks if trade mark checks fail.
A3: Name | B3: Meaning | C3: Strengths | D3: Notes
A4: Hammerwise | B4: Smart about the hammer price. | C4: Clear meaning, memorable
A5: Lotwise | B5: Wise about every lot. | C5: Short, category neutral
A6: BidCeiling | B6: The most you should pay. | C6: Describes the core outcome
A7: Knockdown | B7: Auction term for the fall of the hammer. | C7: Strong auction language | D7: Also means cheap, which fits resellers
A8: MaxBid (SELECTED) | B8: Direct and literal. The most you should pay. | C8: Instantly understood, matches the core output | D8: maxbid.com used by a US auction house and Maxbid is a crypto app name. Generic auction phrase. Trade mark search required.
A9: LotLogic | B9: Logic applied to each lot. | C9: Suits the evidence first positioning
A10: Bidproof | B10: Bids backed by proof. | C10: Reflects transparency principle
A11: Hammerline | B11: The line you do not cross. | C11: Links to the stop line feature

Sheet 22 Risks
A1: Risk Register
A2: Likelihood and impact scored 1 to 5. Rating is a formula.
A3: ID | B3: Category | C3: Risk | D3: Likelihood | E3: Impact | F3: Rating | G3: Mitigation
A4: R01 | B4: Technical | C4: Auction site structure changes break an extractor | D4: 4 | E4: 3 | F4: =D4*E4 -> 12 | G4: Extractor health checks, admin alerts, PDF fallback, versioned extractors
A5: R02 | B5: Technical | C5: Auction site blocks automated access | D5: 3 | E5: 4 | F5: =D5*E5 -> 12 | G5: Managed extraction, rate limits, compliance with terms, partnership approach later
A6: R03 | B6: Data | C6: Sold price data is hard to obtain | D6: 4 | E6: 4 | F6: =D6*E6 -> 16 | G6: Apply for eBay Marketplace Insights early, use auction realised results, build internal outcomes
A7: R04 | B7: Accuracy | C7: Wrong identification leads to a wrong value | D7: 3 | E7: 5 | F7: =D7*E7 -> 15 | G7: Vision on plates, mandatory user confirmation, confidence scoring, evidence visible
A8: R05 | B8: Accuracy | C8: Weak comparables in broad categories | D8: 4 | E8: 4 | F8: =D8*E8 -> 16 | G8: Honest match levels, insufficient evidence state, category rules added progressively
A9: R06 | B9: Commercial | C9: User overbids and blames the platform | D9: 3 | E9: 4 | F9: =D9*E9 -> 12 | G9: Conservative default, stop line, disclaimers, decision support positioning
A10: R07 | B10: Commercial | C10: Cost per catalogue exceeds pricing | D10: 2 | E10: 4 | F10: =D10*E10 -> 8 | G10: Two stage triage, cost logging per job, credit model, caching
A11: R08 | B11: Legal | C11: Breach of third party terms or copyright | D11: 2 | E11: 5 | F11: =D11*E11 -> 10 | G11: No copied images, respect terms, legal review before launch
A12: R09 | B12: Delivery | C12: Build time competes with consulting workload | D12: 4 | E12: 3 | F12: =D12*E12 -> 12 | G12: Tight V1 scope, eight week plan, weekly milestones
A13: R10 | B13: Delivery | C13: Scope creep before design sign off | D13: 3 | E13: 3 | F13: =D13*E13 -> 9 | G13: Decision register controls change. No build until workbook signed off.
A14: R11 | B14: Security | C14: Cross tenant data leak | D14: 1 | E14: 5 | F14: =D14*E14 -> 5 | G14: RLS on all organisation tables, automated RLS tests
A15: R12 | B15: Marketing | C15: Value guides seen as thin or duplicate content | D15: 3 | E15: 4 | F15: =D15*E15 -> 12 | G15: Publish threshold, unique data per page, noindex below threshold, human review of templates
... A23: R20 | B23: Design | C23: Marker yellow confused with the amber warning colour | D23: 2 | E23: 3 | F23: =D23*E23 -> 6 | G23: Yellow only for actions and the bid figure, amber only for warnings with a text label, contrast tests in CI

Sheet 23 Roadmap
A1: Roadmap
A2: Phase 1 is the internal MVP. Build starts only after workbook sign off.
A3: Phase | B3: Timing | C3: Milestone | D3: Deliverables | E3: Exit criteria
A4: Phase 0 | B4: Week 0 | C4: Design sign off | D4: Review this workbook, close open items, apply for eBay Marketplace Insights, confirm service accounts | E4: Signed off workbook
A5: Phase 1 | B5: Week 1 | C5: Foundations | D5: Turborepo monorepo, lint limits, CLAUDE.md and AGENTS.md, packages for tokens, calc and content, Storybook with core primitives, Supabase schema and migrations, auth, organisations, roles, RLS with tests, app shell, manifest. Holding page with waitlist live on the root domain | E5: Signed in user in an organisation. Waitlist collecting emails
A6: Phase 1 | B6: Week 2 | C6: Ingestion | D6: Grays extractor, PDF upload and parsing, lot normalisation, premium terms parsing, job runner setup | E6: Grays and PDF catalogues extracted
A7: Phase 1 | B7: Week 3 | C7: Triage engine | D7: Pickles and Lloyds extractors, triage identification and rough valuation, opportunity score, email on completion | E7: Ranked triage for all three sources
A8: Phase 1 | B8: Week 4 | C8: Triage interface | D8: Triage table, filters, shortlist, credit preview, progress screen | E8: User can shortlist lots
A9: Phase 1 | B9: Week 5 | C9: Deep analysis | D9: Vision identification, confirmation and editing, comparable search across sources, match grading | E9: Evidence panel populated
A10: Phase 1 | B10: Week 6 | C10: Valuation and calculator | D10: Weighting, scenarios, confidence, bid limits, slider, cost lines, cost profiles, GST engine with unit tests matching tab 10 | E10: Bid limits correct to the cent
A11: Phase 1 | B11: Week 7 | C11: After analysis | D11: Transport estimate, watchlist, closing alerts, outcome recording, PDF bid sheet, CSV, mobile bid view | E11: Full journey usable
A12: Phase 1 | B12: Week 8 | C12: Hardening and live use | D12: Cost logging review, error handling, test on real auctions, record outcomes, fix accuracy issues | E12: Internal MVP in use
A13: Phase 2 | B13: Month 3 | C13: Marketing site | D13: Full marketing site from tab 34, try before sign up, onboarding flow, schema, sitemaps, Search Console and Bing Webmaster Tools, Auction Breakdown template, first four breakdowns published | E13: Site live and indexed
A14: Phase 2 | B14: Month 4 | C14: Commercial launch | D14: Stripe billing, credits, free tier, founding member offer to waitlist, legal review, referral programme, lifecycle emails, first category rules | E14: Paying users
... A16: Phase 3 | B16: Month 5 onward | C16: Growth | D16: More auction sources, saved search alerts, margin dashboard, pooled outcomes, partnerships | E16: Expanded product

Sheet 24 Metrics
A1: Success Metrics
A2: Measured during internal use before commercial launch. Targets are proposed and editable.
A3: Metric | B3: Definition | C3: Target
A4: Extraction completeness | B4: Lots extracted correctly as a share of lots in the catalogue | C4: 0.98
A5: Identification accuracy | B5: Deep identifications confirmed without edit | C5: 0.8
A6: Valuation accuracy | B6: Actual resale within 15 percent of expected resale | C6: 0.7
A7: Conservative reliability | B7: Actual resale at or above conservative resale | C7: 0.85
A8: Triage time | B8: Minutes from submission to triage email for 300 lots | C8: 10
A9: Deep analysis time | B9: Minutes per shortlisted lot | C9: 2
A10: Cost per catalogue | B10: Total AUD cost for a 300 lot catalogue at 10 percent shortlist | C10: 25
A11: Profit on target | B11: Won lots achieving at least the target profit | C11: 0.7
A12: Waitlist sign ups | B12: Emails collected before public launch | C12: 500
A13: Visitor to sign up | B13: Share of homepage visitors who create an account | C13: 0.05
A14: Time to first value | B14: Minutes from sign up to first triage result | C14: 5
A15: Activation | B15: New accounts completing a deep analysis within 7 days | C15: 0.4
... A21: Core Web Vitals | B21: Share of public URLs rated Good in Search Console | C21: 0.9

Sheet 25 Open Items
A1: Open Items
A2: Items to close before or during Phase 0.
A3: ID | B3: Item | C3: How to close | D3: Owner | E3: When
A4: O01 | B4: Choose between Inngest and Trigger.dev | C4: Build a small spike of the fan out pattern on each | D4: Ashleigh | E4: Phase 0
A5: O02 | B5: Choose between Firecrawl and Browserbase | C5: Test both on one catalogue from each auction house | D5: Ashleigh | E5: Phase 0
A6: O03 | B6: Choose between Brave Search API and SerpAPI | C6: Compare result quality on 20 sample lots | D6: Ashleigh | E6: Phase 0
A7: O04 | B7: Apply for eBay Marketplace Insights access | C7: Submit application through the eBay developer program | D7: Ashleigh | E7: Phase 0
A8: O05 | B8: Review Grays, Pickles and Lloyds terms of use | C8: Read terms and record any restrictions on automated access | D8: Ashleigh | E8: Phase 0
A9: O06 | B9: Which categories get specific rules first | C9: Rank by what we buy most and where generic matching is weakest | D9: Ashleigh and Jason | E9: Phase 1
A10: O07 | B10: Calibrate matching and confidence weights | C10: Compare against recorded outcomes after the first 30 won lots | D10: Ashleigh | E10: Phase 1
A11: O08 | B11: Product name | C11: Closed. MaxBid selected | D11: Ashleigh and Jason | E11: Closed
A12: O09 | B12: Validate pricing tiers | C12: Interview five resellers and test willingness to pay | D12: Ashleigh | E12: Phase 2
A13: O10 | B13: Legal review of terms and disclaimers | C13: Engage a lawyer before public launch | D13: Ashleigh | E13: Phase 2
A14: O11 | B14: Secure MaxBid | C14: Register maxbid.com.au under an ABN, search IP Australia for MaxBid in classes 9, 35 and 42, register the business name with ASIC, reserve social handles. Needed before the Week 1 holding page | D14: Ashleigh and Jason | E14: Phase 0
... A19: O16 | B19: Choose visual regression tool | C19: Chromatic or Playwright screenshots, based on cost and workflow | D19: Ashleigh | E19: Phase 1

Sheet 26 Config Principles
A1: Configuration and Transparency Principles
A2: The rules every setting, screen and message must follow.
A3: ID | B3: Principle | C3: What it means in practice
A4: CP01 | B4: The platform is a helper | C4: It advises. It never makes or blocks a bidding decision. The user may know more than the evidence, so the user can always enter their own figure and proceed.
A5: CP02 | B5: Block only to protect others | C5: The platform blocks an action only when it would change data other users rely on, breach security or permissions, spend credits the organisation does not have, or alter the fixed method. Everything else is a warning.
A6: CP03 | B6: Private by default | C6: Every user change applies to that lot in that organisation only. No user action changes what another organisation sees.
A7: CP04 | B7: Shared data is moderated | C7: Corrections that would improve shared data go to an admin review queue. They apply to everyone only after approval.
A8: CP05 | B8: The method is fixed and public | C8: Bid maths, GST, evidence weights, match levels and confidence scoring are hard coded, versioned and explained to users. They change only through a released version with a public changelog.
A9: CP06 | B9: Defaults are editable, the method is not | C9: Operational defaults such as premium fallbacks and asking discounts are admin settings with a change log. Organisations set their own commercial defaults. Nobody edits the method through settings.
A10: CP07 | B10: Every figure declares its source | C10: Each number carries one provenance tag: Verified, Extracted, Estimated or Your input. AI generated content carries an additional AI label.
A11: CP08 | B11: Say what we do not know | C11: Every lot lists the sources searched, what was not found and what the platform cannot verify. Absence of evidence is shown, never hidden.
A12: CP09 | B12: User figures are never presented as system figures | C12: When a user overrides a value, the override is marked, the system value stays visible and system confidence is not applied to the user's figure.
A13: CP10 | B13: Nothing silently changes | C13: Method updates, data refreshes and overrides are always visible. Past results stay reproducible under the method version that produced them.
A14: CP11 | B14: Plain factual language | C14: Warnings and disclaimers state the risk and the reason in plain, neutral words. No legal padding in the interface, full terms one tap away.
... A16: CP12 | B16: Disclaimers where the risk is | C16: Short notes appear beside the figure they relate to, not as page banners. Every export carries the footer disclaimer, source tags and analysis date.

Sheet 27 Settings Matrix
A1: Settings Matrix
A2: Where each setting lives, who can change it and how far the change reaches. Lower layers override higher layers unless locked.
A3: ID | B3: Setting | C3: Layer | D3: Type | E3: Who can change | F3: Org lock | G3: Default | H3: Reach of change | I3: Notes
A4: CS01 | B4: Bid limit formulas | C4: Platform | D4: Hard coded | E4: Code release | F4: No | G4: Tab 10 formulas | H4: Everyone | I4: Visible in How this was calculated
A5: CS02 | B5: Calculation order and rounding | C5: Platform | D5: Hard coded | E5: Code release | F5: No | G5: Round to whole dollars for display, cents internally | H5: Everyone
A6: CS03 | B6: GST rate | C6: Platform | D6: Hard coded | E6: Code release | F6: No | G6: 10 percent | H6: Everyone | I6: Legislative change handled by release
A7: CS04 | B7: Match level definitions | C7: Platform | D7: Hard coded | E7: Code release | F7: No | G7: Tab 08 | H7: Everyone | I7: Published on methodology page
A8: CS05 | B8: Evidence type weights | C8: Platform | D8: Hard coded | E8: Code release | F8: No | G8: Tab 08 | H8: Everyone | I8: Versioned
A9: CS06 | B9: Recency decay | C9: Platform | D9: Hard coded | E9: Code release | F9: No | G9: Tab 08 | H9: Everyone | I9: Versioned
A10: CS07 | B10: Confidence formula and bands | C10: Platform | D10: Hard coded | E10: Code release | F10: No | G10: Tab 08 | H10: Everyone | I10: Versioned
A11: CS08 | B11: Minimum evidence threshold | C11: Platform | D11: Hard coded | E11: Code release | F11: No | G11: Three comparables and combined weight 1.5 | H11: Everyone | I11: Versioned
A12: CS09 | B12: Scenario percentiles | C12: Platform | D12: Hard coded | E12: Code release | F12: No | G12: 25th, median, 75th | H12: Everyone | I12: Versioned
A13: CS10 | B13: User supplied comparable weight | C13: Platform | D13: Hard coded | E13: Code release | F13: No | G13: 0.50 | H13: Everyone | I13: Versioned
A14: CS11 | B14: Provenance tag definitions | C14: Platform | D14: Hard coded | E14: Code release | F14: No | G14: Tab 29 | H14: Everyone
A15: CS12 | B15: Core disclaimer wording | C15: Platform | D15: Hard coded | E15: Code release with terms version | F15: No | G15: Tab 30 | H15: Everyone | I15: Material change forces re acceptance
A16: CS13 | B16: Stale data threshold | C16: Platform | D16: Hard coded | E16: Code release | F16: No | G16: 7 days | H16: Everyone
A17: CS14 | B17: Price cache period | C17: Platform | D17: Hard coded | E17: Code release | F17: No | G17: 7 days | H17: Everyone
A18: CS15 | B18: Accuracy publishing minimum | C18: Platform | D18: Hard coded | E18: Code release | F18: No | G18: 30 outcomes per category | H18: Everyone
A19: CS16 | B19: Buyer's premium fallback per platform | C19: Platform | D19: Admin setting | E19: Platform admin, logged | F19: No | G19: Per platform | H19: New analyses | I19: Used only when extraction fails
A20: CS17 | B20: GST on premium fallback per platform | C20: Platform | D20: Admin setting | E20: Platform admin, logged | F20: No | G20: Yes | H20: New analyses
A21: CS18 | B21: Asking to selling discount by category | C21: Platform | D21: Admin setting | E21: Platform admin, logged | F21: No | G21: 10 percent | H21: New valuations | I21: Stamped on each valuation
A22: CS19 | B22: Category tree | C22: Platform | D22: Admin setting | E22: Platform admin, logged | F22: No | H22: Everyone
A23: CS20 | B23: We cannot verify items by category | C23: Platform | D23: Admin setting | E23: Platform admin, logged | F23: No | G23: Tab 29 | H23: Everyone
A24: CS21 | B24: Extractor enabled per platform | C24: Platform | D24: Admin setting | E24: Platform admin, logged | F24: No | G24: On | H24: Everyone | I24: Switch off a broken extractor without a deploy
A25: CS22 | B25: Tier limits and credit prices | C25: Platform | D25: Admin setting | E25: Platform admin, logged | F25: No | G25: Tab 18 | H25: Everyone | I25: Phase 2
A26: CS23 | B26: Feature flags | C26: Platform | D26: Admin setting | E26: Platform admin, logged | F26: No | H26: Targeted
A27: CS24 | B27: GST registered | C27: Organisation | D27: Org setting | E27: Owner or admin | F27: Fixed | G27: No | H27: Organisation | I27: Recalculates open lots
A28: CS25 | B28: Base location | C28: Organisation | D28: Org setting | E28: Owner or admin | F28: Fixed | H28: Organisation | I28: Users may set a personal base
A29: CS26 | B29: Cost profiles | C29: Organisation | D29: Org setting | E29: Owner, admin or buyer | F29: Fixed | G29: One default profile | H29: Organisation | I29: Lock prevents members editing profiles
A30: CS27 | B30: Default cost profile | C30: Organisation | D30: Org setting | E30: Owner or admin | F30: Fixed | H30: Organisation
A31: CS28 | B31: Default profit mode | C31: Organisation | D31: Org setting | E31: Owner or admin | F31: Fixed | G31: Dollars | H31: Organisation
A32: CS29 | B32: Default target profit | C32: Organisation | D32: Org setting | E32: Owner or admin | F32: Floor | H32: Organisation | I32: Floor means members can raise but not lower
A33: CS30 | B33: Minimum acceptable profit | C33: Organisation | D33: Org setting | E33: Owner or admin | F33: Floor | H33: Organisation | I33: Drives absolute maximum bid
A34: CS31 | B34: Default resale scenario | C34: Organisation | D34: Org setting | E34: Owner or admin | F34: Fixed | G34: Conservative | H34: Organisation
A35: CS32 | B35: Transport rate per km and base fee | C35: Organisation | D35: Org setting | E35: Owner or admin | F35: Floor | G35: In cost profile | H35: Organisation
A36: CS33 | B36: Default alert lead time | C36: Organisation | D36: Org setting | E36: Owner or admin | F36: No | G36: 30 minutes | H36: Organisation
A37: CS34 | B37: Members and roles | C37: Organisation | D37: Org setting | E37: Owner or admin | F37: n/a | H37: Organisation
A38: CS35 | B38: Personal target profit | C38: User | D38: User preference | E38: The user | F38: Subject to org lock | G38: Inherits org | H38: That user
A39: CS36 | B39: Personal default cost profile | C39: User | D39: User preference | E39: The user | F39: Subject to org lock | G39: Inherits org | H39: That user
A40: CS37 | B40: Personal base location | C40: User | D40: User preference | E40: The user | F40: Subject to org lock | G40: Inherits org | H40: That user
A41: CS38 | B41: Alert lead time | C41: User | D41: User preference | E41: The user | F41: No | G41: Inherits org | H41: That user
A42: CS39 | B42: Notification channels | C42: User | D42: User preference | E42: The user | F42: No | G42: Email and push | H42: That user
A43: CS40 | B43: Theme | C43: User | D43: User preference | E43: The user | F43: No | G43: Follow system | H43: That user
A44: CS41 | B44: Table density and columns | C44: User | D44: User preference | E44: The user | F44: No | G44: Standard | H44: That user
A45: CS42 | B45: Default triage filters | C45: User | D45: User preference | E45: The user | F45: No | G45: None | H45: That user
A46: CS43 | B46: Identification (brand, model, year, specs) | C46: Lot | D46: Lot input | E46: Buyer or above | F46: No | G46: System identification | H46: That lot in that org | I46: Can also be submitted for shared review
A47: CS44 | B47: Resale scenario | C47: Lot | D47: Lot input | E47: Buyer or above | F47: Subject to org lock | G47: Inherited | H47: That lot in that org
A48: CS45 | B48: Resale price override | C48: Lot | D48: Lot input | E48: Buyer or above | F48: No | G48: System scenario value | H48: That lot in that org | I48: Tagged Your input
A49: CS46 | B49: Buyer's premium rate | C49: Lot | D49: Lot input | E49: Buyer or above | F49: No | G49: Extracted | H49: That lot in that org | I49: Wrong extraction can be reported for review
A50: CS47 | B50: GST on hammer and premium flags | C50: Lot | D50: Lot input | E50: Buyer or above | F50: No | G50: Extracted | H50: That lot in that org
A51: CS48 | B51: Cost line items | C51: Lot | D51: Lot input | E51: Buyer or above | F51: Floor where profile is locked | G51: Cost profile | H51: That lot in that org
A52: CS49 | B52: Transport amount | C52: Lot | D52: Lot input | E52: Buyer or above | F52: No | G52: Distance estimate | H52: That lot in that org
A53: CS50 | B53: Profit mode and target | C53: Lot | D53: Lot input | E53: Buyer or above | F53: Subject to org lock | G53: Inherited | H53: That lot in that org
A54: CS51 | B54: Proposed bid (slider) | C54: Lot | D54: Lot input | E54: Buyer or above | F54: No | G54: Target bid | H54: That lot in that org | I54: Never locked. Warnings only.
A55: CS52 | B55: Exclude comparable | C55: Lot | D55: Lot input | E55: Buyer or above | F55: No | G55: Included | H55: That lot in that org | I55: Reason required
A56: CS53 | B56: Add user comparable | C56: Lot | D56: Lot input | E56: Buyer or above | F56: No | H56: That organisation | I56: Private to organisation
A57: CS54 | B57: Watchlist | C57: Lot | D57: Lot input | E57: Buyer or above | F57: No | G57: Off | H57: That organisation
A58: CS55 | B58: Outcome | C58: Lot | D58: Lot input | E58: Buyer or above | F58: No | H58: That organisation | I58: Pooled use needs consent

Sheet 28 Override Rules
A1: Override Rules and Responses
A3: Precedence
A4: Resolution order | B4: Lot value, then User preference, then Organisation setting, then Platform default. The first value found is used.
A5: Fixed lock | B5: The organisation value is used at every lower layer. Lower layers cannot save a different value.
A6: Floor lock | B6: Lower layers can set a value equal to or stricter than the organisation value but never less strict. For profit this means higher, never lower.
A7: Enforcement | B7: Locks are enforced by the database on every write, so the API and the interface behave the same.
A8: Locks and bidding | B8: Locks shape the calculated bid limits. They never stop a user moving the bid slider. A bid beyond a limit produces a warning, not a block.
A9: Hard coded items | B9: No layer can override them. They appear read only with a link to the methodology.
A11: Override display
A12: Marker | B12: Every overridden field shows a Your input tag and a small reset icon.
A13: System value | B13: The system value stays visible beside or beneath the override, never replaced.
A14: Reset | B14: One click restores the current system value. The reset is recorded in the lot history.
A15: Override summary | B15: Each lot has a Changes from system panel listing field, system value, your value, who changed it and when.
A16: Team visibility | B16: All organisation members see overrides and who made them.
A17: Confidence | B17: System confidence applies only to system values. When the resale price is overridden the confidence badge reads System confidence and the figure in use is tagged Your input.
A19: Situation responses
A20: Situation | B20: Reason | C20: Response | D20: Behaviour | E20: Message
A21: Proposed bid above target | B21: Slider enters amber zone | C21: Inform | D21: Zone label changes to Below target.
A22: Proposed bid above absolute maximum | B22: Profit falls below minimum | C22: Warn | D22: Warning shown beside the bid. User can proceed. | E22: DS05
A23: Proposed bid above break even | B23: Estimated loss | C23: Warn | D23: Red warning with estimated loss amount. User can proceed. | E23: DS06
A24: Profit only met on optimistic scenario | B24: Relies on favourable outcome | C24: Warn | D24: Warning on the lot and in the bid sheet. | E24: DS07
A25: Resale override entered | B25: User knows more than evidence | C25: Inform | D25: Value tagged Your input, system value retained. | E25: DS04
A26: Resale override above optimistic value | B26: Above all evidence | C26: Warn | D26: Warning that the figure is above every comparable found. | E26: DS04
A27: Insufficient evidence | B27: No defensible comparable | C27: Inform | D27: No system bid. Resale field opens for user entry. | E27: DS03
A28: Identification not confirmed | B28: Values may change | C28: Inform | D28: Unconfirmed badge on the lot and bid sheet. | E28: DS14
A29: Selling fees blank | B29: Max bid may be inflated | C29: Warn | D29: Flag on lot row and bid sheet. | E29: DS15
A30: Buyer's premium from fallback | B30: Extraction failed | C30: Warn | D30: Premium tagged Estimated with note to check terms. | E30: DS12
A31: Price older than seven days | B31: Stale evidence | C31: Warn | D31: Stale tag with refresh action. | E31: DS09
A32: All comparables excluded | B32: No evidence left | C32: Warn | D32: Lot moves to insufficient evidence until a comparable is restored or a resale is entered. | E32: DS17
A33: Newer method available | B33: Result uses older method | C33: Inform | D33: Prompt to recalculate. Old result remains viewable. | E33: DS19
A34: Edit below an organisation Floor lock | B34: Breaches organisation rule | C34: Block | D34: Field rejects the value and names the lock and its owner.
A35: Edit a Fixed locked setting | B35: Breaches organisation rule | C35: Block | D35: Field read only with lock icon.
A36: Viewer attempts an edit | B36: Role permission | C36: Block | D36: Edit controls hidden.
A37: Deep analysis beyond available credits | B37: Billing integrity | C37: Block | D37: Shortlist cannot be confirmed. Shows credits needed.
A38: Edit shared data directly | B38: Protects other users | C38: Block | D38: Offer Submit for review instead.
A39: Change hard coded method | B39: Method integrity | C39: Block | D39: Read only with methodology link.
A40: Material terms change unaccepted | B40: Legal | C40: Block | D40: Acceptance screen before continuing. | E40: DS01

Sheet 29 Transparency
A1: Transparency Specification
A3: Provenance tags
A4: Tag | B4: Definition | C4: Examples
A5: Verified | B5: A sold result or recorded outcome with a checkable source. | C5: Auction realised price, marketplace sold listing, your recorded resale.
A6: Extracted | B6: Read directly from a source page without calculation. | C6: Advertised price, auction premium rate, closing time.
A7: Estimated | B7: Calculated or inferred by the platform, including fallbacks. | C7: Resale scenarios, transport, AI identification, premium fallback.
A8: Your input | B8: Entered or changed by a member of your organisation. | C8: Resale override, repair cost, user supplied comparable.
A9: AI generated label | B9: An additional label shown alongside the tag on any identification, match reason, difference list or summary produced by AI. It never replaces the provenance tag.
A11: Evidence display rules
A12: Every price | B12: Shows source name, link, date checked, provenance tag and match level.
A13: Data age | B13: Date checked on every price. Stale tag and refresh action after seven days.
A14: Searched and not found | B14: Every lot lists each source queried, the number of results and what was not found. Example: eBay 4 results, no exact match. Grays past results 0 results. Manufacturer site new price not found.
A15: Adjustments | B15: Any price adjustment is shown as original price, adjustment percentage, reason and adjusted price.
A16: Weights | B16: Each comparable's combined weight is visible in the evidence panel.
A17: How this was calculated | B17: Expander on every bid limit. Shows the resale scenario and its evidence summary, every cost line with its tag, premium and GST flags, the formula in words and the method version.
A19: We cannot verify
A20: Category | B20: Items the platform cannot verify
A21: All categories | B21: Condition, working order, completeness, hidden damage, accuracy of the auction description, ownership and any money owing on the item.
A22: Vehicles and trailers | B22: Odometer accuracy, service history, registration status, finance owing (check the PPSR), accident history.
A23: Machinery and plant | B23: Operating hours, tooling and accessories included, electrical supply requirements, guarding and compliance, wear on critical components.
A24: Power tools | B24: Battery health, chargers and batteries included, motor wear.
A25: Electronics and IT | B25: Activation or account locks, battery health, data wiping, licences included.
A26: Commercial kitchen | B26: Gas and electrical compliance, refrigeration performance, parts availability.
A28: Category list | B28: Category items are admin settings (tab 27). The general list always shows. Category items are added to it.
A30: Spec sheet source classes
A31: Source class | B31: Meaning | C31: How it is presented
A32: Model specifications | B32: Published by the manufacturer, a dealer or a specification database for this model. | C32: True of the model. Not confirmed for this unit.
A33: Observed on this lot | B33: Read from the lot photos, such as a data plate or a visible unit. | C33: AI generated label. User can confirm.
A34: Auctioneer stated | B34: Taken from the auction listing. | C34: Extracted. Not independently checked.
A35: Not verified | B35: Options, fitted units, hours or condition that no source confirmed for this lot. | C35: Shown so gaps are visible.
A37: Conflicts | B37: When sources disagree, both values show side by side with a conflict flag. The platform does not pick a winner.
A38: Optional equipment | B38: Known options for the model are listed and marked Observed, Stated, Absent or Not verified for this lot.
A39: Not identified | B39: If the item cannot be identified from text and photos, no specifications are added. The user can enter brand and model, tagged Your input, to trigger enrichment.
A40: No guessing | B40: The platform never infers a brand or model to fill a gap.
A42: Delivery | B42: Spec sheet section on lot detail and a downloadable PDF spec sheet. Enrichment runs in deep analysis and is included in the credit.

Sheet 30 Disclaimers
A1: Disclaimer and Message Library
A2: Plain, factual and neutral. Values in square brackets are filled by the system. Legal review required before launch.
A3: ID | B3: Placement | C3: Trigger | D3: Text
A4: DS01 | B4: Sign up and material terms change | C4: Clickwrap | D4: This platform gives estimates to support your decisions. It does not give valuations, financial advice or tax advice. Estimates are based on public information at the date checked and can be wrong. Inspect items and read the auction terms before bidding. You are responsible for your bids.
A5: DS02 | B5: Every lot detail footer | C5: Always | D5: Estimate only, based on the evidence listed and checked on [date]. Condition and working order have not been verified.
A6: DS03 | B6: Insufficient evidence | C6: Lot has no defensible comparable | D6: We could not find enough reliable evidence to estimate a resale value for this lot. Enter your own resale estimate to calculate a bid.
A7: DS04 | B7: Resale override | C7: User enters own resale | D7: This bid uses your resale estimate of [amount], not the system estimate of [amount]. System confidence does not apply to your figure.
A8: DS05 | B8: Above absolute maximum | C8: Proposed bid exceeds limit | D8: This bid is above your absolute maximum of [amount]. Estimated profit is below your minimum of [amount].
A9: DS06 | B9: Above break even | C9: Proposed bid exceeds break even | D9: At this bid you would make an estimated loss of [amount].
A10: DS07 | B10: Optimistic reliance | C10: Target only met on optimistic value | D10: Your profit target is only met at the optimistic resale value. That value needs good condition and strong demand.
A11: DS08 | B11: Specification mismatch | C11: Higher or lower specification comparable | D11: No exact match was found. This comparable has [more or fewer] features than the lot, so its price has been adjusted [down or up] by [percent].
A12: DS09 | B12: Stale price | C12: Checked more than seven days ago | D12: This price was checked on [date]. Refresh to check current listings.
A13: DS10 | B13: GST note | C13: Calculator panel | D13: GST is calculated from your profile setting and the auction terms. This is not tax advice. Confirm your position with your accountant.
A14: DS11 | B14: Transport estimate | C14: Transport line | D14: Estimated from road distance of [km] at your rate. Actual quotes may differ.
... A38: DS22 | B38: Submit for review | C38: User submits a shared data correction | D38: Thanks. Your correction applies to your organisation now. It will apply to everyone once reviewed.
A40: Placement and style rules
A41: ID | B41: Rule | C41: Applies to | D41: Detail
A42: PR01 | B42: Subtle by default | C42: All notes | D42: Muted text at 12px directly beneath the element it qualifies, with an info icon that opens the full text. No page banners.
A43: PR02 | B43: Warnings stand out | C43: DS05, DS06, DS07, DS15, DS24 | D43: Amber styling beside the figure they affect. Notes use muted grey.
A44: PR03 | B44: One note per section | C44: All notes | D44: The same note never repeats within one panel or card.
A45: PR04 | B45: Only one blocking message | C45: DS01 | D45: The clickwrap is the only disclaimer that interrupts the user. Everything else sits in context.
A46: PR05 | B46: Consistent phrasing | C46: DS35 | D46: Where a check is recommended, use DS35 word for word.
A47: PR06 | B47: Exports | C47: DS16, DS23 | D47: Every PDF and CSV carries DS16. Spec sheets also carry DS23.
A49: Coverage map
A50: ID | B50: Screen or element | C50: Messages | D50: Style
A51: CM01 | B51: Sign up and terms change | C51: DS01 | D51: Clickwrap
A52: CM02 | B52: Triage table | C52: DS21 | D52: Muted note under table header
A53: CM03 | B53: Lot detail | C53: DS02 | D53: Muted footer
A54: CM04 | B54: Identification card | C54: DS13, DS14 | D54: Muted note and badge
A55: CM05 | B55: Not identified lot | C55: DS25 | D55: Muted note beside entry field
A56: CM06 | B56: Spec sheet section | C56: DS23, DS24, DS34 | D56: Muted header, amber conflict flags, checklist footer
A57: CM07 | B57: Evidence panel | C57: DS26, DS08, DS09, DS33 | D57: Muted header, inline notes per comparable
A58: CM08 | B58: Cheapest advertised and new price | C58: DS27, DS28 | D58: Muted note under figure
A59: CM09 | B59: Searched and not found panel | C59: DS29 | D59: Muted header
A60: CM10 | B60: We cannot verify panel | C60: DS30 | D60: Muted header
A61: CM11 | B61: Insufficient evidence lot | C61: DS03 | D61: Muted note in resale field
... A71: CM21 | B71: Accuracy page | C71: DS20 | D71: Page header

Sheet 31 Governance
A1: Governance
A3: Method versioning
A4: Version format | B4: Major, minor and patch numbers. Major changes the maths or scoring approach. Minor changes weights or thresholds. Patch fixes errors without changing intended results.
A5: Release process | B5: Change proposed with evidence from outcome data, tested against recorded outcomes, approved, released with a changelog entry and a new method_versions row.
A6: Existing results | B6: Every valuation keeps the version that produced it. Users see a newer method prompt and choose when to recalculate. The old result stays viewable.
A7: Public changelog | B7: Every method release and data source change is published with a plain English summary.
A9: Correction review workflow
A10: Step | B10: Stage | C10: What happens
A11: 1 | B11: Submit | C11: User reports a problem or submits a correction with optional evidence. Their own organisation sees the change immediately.
A12: 2 | B12: Queue | C12: If the change would alter shared data it creates a correction review. The submitting organisation is hidden from other users.
A13: 3 | B13: Review | C13: Platform admin checks the evidence and approves, rejects or edits the correction.
A14: 4 | B14: Apply | C14: Approved changes update the shared record with provenance recorded and an audit entry.
A15: 5 | B15: Notify | C15: Submitter is told the outcome. Affected analyses in other organisations show a refreshed data notice, never a silent change.
A17: Problem reports
A18: Where | B18: Report a problem on every lot, identification and comparable.
A19: Categories | B19: Wrong item, wrong price, broken link, wrong premium, other.
A20: Response targets | B20: Acknowledged automatically. Reviewed within two business days during internal use. Targets reset at commercial launch.
A21: Use | B21: Reports feed extractor fixes, correction reviews and method calibration.
A23: Accuracy publishing
A24: Minimum sample | B24: At least 30 recorded outcomes in a category before its accuracy is published.
A25: Measures | B25: Share of actual resales within 15 percent of expected resale, and share at or above conservative resale.
A26: Update frequency | B26: Monthly, stamped with method version and period.
A27: Categories below minimum | B27: Shown as Not enough data yet.
A28: Phase | B28: Internal tracking from the MVP. Public page at or after commercial launch.
A30: Admin setting changes
A31: Change log | B31: Every platform setting change records old value, new value, who, when and a required reason.
A32: Effect | B32: Applies to new analyses and valuations. Existing results keep the values stamped on them.
A33: Access | B33: Platform admins only. Ashleigh during internal use.

Sheet 32 Brand
A1: Brand
A2: MaxBid | maxbid.com.au
A3: Positioning
A4: Positioning statement | B4: For Australian resellers who buy at auction, MaxBid tells you what a lot is really worth and the most you should pay, with every number backed by evidence you can check.
A5: Category | B5: Auction bid intelligence.
A6: Core promise | B6: Know the most you should pay before the hammer falls.
A7: Proof points | B7: Evidence on every figure. Full acquisition costs including premium, GST and transport. Conservative by default. Public method and accuracy.
A8: Enemy | B8: Bidding on gut feel, and research that takes longer than the auction.
A10: Personality: Sharp insider
A11: Confident | B11: Knows how auctions work and explains it clearly. States what the evidence shows and what it does not.
A12: Warm and direct | B12: Talks to the reader as a knowledgeable friend would. Uses you and we.
A13: Plain speaking | B13: Complete sentences in everyday words. Every figure and term is explained. Australian English.
A14: On the buyer's side | B14: Protects the user's profit, including from the excitement of a live auction.
A15: Wit | B15: Allowed only in taglines and social posts, and only when the meaning is still obvious. Never in explanations, instructions, figures, warnings or disclaimers.
A17: Writing rules
A18: ID | B18: Rule | C18: Detail
A19: WR01 | B19: Write complete sentences | C19: Every sentence in body copy has a subject and a verb. No sentence fragments such as Every cost. Every credit. One number.
A20: WR02 | B20: Use everyday words | C20: Choose the word a customer would use. Say counts more towards the estimate rather than weighs the most.
A21: WR03 | B21: Explain terms the first time | C21: Define target bid, absolute maximum, stop line, comparable, buyer's premium, triage and credit where they first appear on a page.
A22: WR04 | B22: Say who does what | C22: Use active voice. We reduced the price by 10 percent, rather than Price adjusted.
A23: WR05 | B23: Keep the reason | C23: One idea per sentence, but keep the linking words such as because, so and which that explain why.
A24: WR06 | B24: No slang or metaphors in explanations | C24: Avoid phrases such as knock out, receipts, your number or marks. Say what the thing actually is.
A25: WR07 | B25: Tell people what they can do | C25: Instructions say the action and the result. Select any square to see where the price came from.
A26: WR08 | B26: Headings make sense alone | C26: Short headings are fine, but every heading is followed by a plain sentence that explains the section.
A27: WR09 | B27: Name every figure | C27: Always say what a number is. An estimated profit of $4,000, rather than $4,000 on its own.
A28: WR10 | B28: Reading level | C28: Aim for a reading age of about 12 to 14 years. Check key pages with a readability tool before publishing.
A29: WR11 | B29: Data labels | C29: Short uppercase labels such as TARGET BID are allowed only as labels on figures, never as sentences.
A30: WR12 | B30: House rules | C30: Australian English. No dashes of any kind. No keynote style contrasting sentences.
A32: Before and after
A33: Before | B33: After
A34: Every comparable we found, on one line. Sold results weigh the most. Close matches weigh more than loose ones. Tap any mark to see its source, and knock out the ones you think are wrong. | B34: This chart shows every comparable sale and listing we found for this machine, placed by price. Prices from completed sales count more towards the estimate than asking prices. Items that closely match this machine also count more than items that are only similar. Select any square to see where the price came from. If you think a comparable is wrong, you can remove it and the estimate will update.
A35: Every cost. Every credit. One number. | B35: This docket adds up every cost of buying the lot, including the buyer's premium, GST, transport and repairs. It then works out the most you should pay to make your target profit.
A36: MaxBid gives you your number before the hammer falls. | B36: MaxBid works out the most you should pay for a lot before the auction closes.
A37: Auction listings are written in a hurry. | B37: Auction listings are often short and missing important details.
A38: They paid past break even. You kept your margin. | B38: The winning bidder paid more than the price where you would break even. You did not overpay.
A39: Triage is free. Credits pay for deep analysis. | B39: Ranking every lot in a catalogue is free. A detailed analysis of one lot uses one credit.
A41: Voice examples
A42: Headline | B42: Know the most you should pay before the hammer falls.
A43: Social line | B43: Stop bidding on vibes.
A44: Empty state | B44: Your watchlist is empty. Add lots from any analysis to track them here.
A45: Warning | B45: At this bid you would make an estimated loss of $1,240.
A47: Tagline candidates
A48: ID | B48: Tagline | C48: Use
A49: T01 | B49: Know the most you should pay before the hammer falls. | C49: Primary. Clear promise.
A50: T02 | B50: See the evidence behind every bid. | C50: Transparency angle.
A51: T03 | B51: Every cost of buying a lot, added up into one clear figure. | C51: Descriptive. Good for ads.
A52: T04 | B52: Stop bidding on vibes. | C52: Social and campaign line.
A53: T05 | B53: The most you should pay, with the working shown. | C53: Calculator angle.
A55: Logo direction
A56: Wordmark | B56: MaxBid in Barlow bold. Always written MaxBid: capital M, capital B, one word. A marker yellow stop line sits beneath Bid.
A57: Mark | B57: The stop line: a heavy horizontal bar in marker yellow, taken from the bid limit marker. It doubles as the active tab marker and loading motif.
A58: Favicon and app icon | B58: Marker yellow stop line on a navy square with a thin cyan frame.
A59: Consistency | B59: One name (MaxBid), one domain (maxbid.com.au), one description used everywhere: site, social, directories and schema. Pair the name with Australia in bios and early content so search engines and AI models separate MaxBid from overseas businesses with similar names.

Sheet 33 Visual Identity
A1: Visual Identity and CSS
A2: Blueprint direction, based on engineering drawings. Signed off 22 September 2026.
A3: Brand palette
A4: Colour | B4: Value | C4: Role | D4: Rule
A5: Blueprint navy | B5: #0E2A47 | C5: Header, footer and feature panels | D5: Always paired with white text and cyan lines
A6: Drafting white | B6: #F4F7FA | C6: Page background | D6: Cool off white
A7: Line cyan | B7: #7FC8F8 | C7: Frame lines, labels and title blocks on navy | D7: Decorative and label use only on navy
A8: Marker yellow | B8: #FFD23F | C8: Primary buttons, stop line, most you should bid | D8: Always with ink text. Never used for status
A9: Pen blue | B9: #1B6FD1 | C9: Links, icons, index numbers, Your input tag
A10: Ink | B10: #0E1B2B | C10: Text
A11: Status colours | B11: #1E7A52, #B45309, #B91C1C | C11: On target, below target, loss risk | D11: Always with a text label
A13: Typography
A14: Role | B14: Font | C14: Use | D14: Rule
A15: Headings and figures | B15: Barlow 700 to 800 | C15: Headlines, bid figures, card titles | D15: Fluid size with clamp. Normal capitalisation
A16: Body and interface | B16: Barlow 400 to 600 | C16: Body text, buttons, forms | D16: Tabular figures on for every number
A17: Labels and data | B17: Space Mono 400 to 700 | C17: Lot numbers, data labels, title blocks, tags | D17: Uppercase labels with wide letter spacing
A19: Blueprint details
A20: ID | B20: Detail | C20: Specification
A21: B01 | B21: Drawing sheet frame | C21: Navy panels carry a double inset frame in line cyan, like the border of a drawing sheet.
A22: B02 | B22: Title block | C22: The homepage header carries a small title block in the corner: project, sheet and region.
A23: B03 | B23: Detail labels | C23: Result cards are labelled DETAIL A, DETAIL B and so on in a navy tab, like views on a drawing.
A24: B04 | B24: Mono labels | C24: Small uppercase Space Mono labels above figures, such as MOST YOU SHOULD BID.
A25: B05 | B25: Leader dots | C25: Dotted leader lines connect labels to figures in cost lists and side panels.
A26: B06 | B26: Measurement lines | C26: Dimension lines with end ticks mark totals, such as the split bar on the homepage.
A27: B07 | B27: Line icons | C27: Simple 1.4px stroke icons in pen blue for categories and actions.
A28: B08 | B28: Sharp geometry | C28: 2px corner radius. Hairline borders instead of shadows.
A29: B09 | B29: Yellow means act | C29: Marker yellow appears only on the main action and the most you should bid figure, so the eye goes there first.
A30: B10 | B30: Avoid | C30: Gradient blobs, glassmorphism, stock photos, generic AI sparkle icons, soft rounded cards with heavy shadows.
A32: CSS architecture
A33: ID | B33: Area | C33: Rule
A34: C01 | B34: Tokens | C34: All colour, type, spacing, radius and motion values defined once as CSS variables in the Tailwind v4 theme. Semantic names only: ink, surface, accent, zone_green.
A35: C02 | B35: Theming | C35: Light pages by default with a navy panel token set for headers and feature panels. A dark app theme can be added later from the same tokens.
A36: C03 | B36: Components | C36: shadcn/ui restyled to the tokens. One component library shared by site and app.
A37: C04 | B37: Layout | C37: CSS grid for page structure, container queries for cards, logical properties for spacing.
A38: C05 | B38: Fluid type | C38: clamp based type scale so headings scale smoothly from phone to desktop.
A39: C06 | B39: Focus | C39: 3px marker yellow focus outline with offset on every interactive element. Never removed.
A40: C07 | B40: Performance | C40: Marketing pages are server components with minimal client JavaScript. Fonts self hosted. Images through next/image in AVIF or WebP.
A41: C08 | B41: Motion | C41: Durations and easing as tokens. All animation wrapped in a reduced motion media query.
A42: C09 | B42: Density | C42: App tables support standard and comfortable density through a single token switch.
A43: C10 | B43: Quality gates | C43: Visual regression snapshots of key components, contrast tests and axe checks in CI.

Sheet 34 Website SEO
A1: Public Website and SEO
A2: maxbid.com.au is the marketing site. app.maxbid.com.au is the app and is noindex.
A3: Path | B3: Page | C3: Search intent | D3: Schema | E3: Content notes
A4: / | B4: Home | C4: Brand and product: auction bid calculator Australia | D4: WebSite, Organization, SoftwareApplication | E4: Drawing sheet header with search tabs, sample result detail cards, category tiles, auctions closing soon, split bar explanation, Auction Breakdown panel, popular guides
A5: /how-it-works | B5: How it works | C5: How to value auction lots | D5: WebPage, HowTo | E5: Journey from tab 06 with real UI
A6: /pricing | B6: Pricing | C6: Pricing intent | D6: SoftwareApplication with offers | E6: Tiers from tab 18, credit explainer, FAQ
A7: /methodology | B7: Methodology | C7: How auction valuations work | D7: Article | E7: Public version of tabs 08 and 10. Key trust and AI citation asset
A8: /accuracy | B8: Accuracy | C8: Is it accurate | D8: Dataset, Article | E8: Published accuracy by category (tab 31)
A9: /changelog | B9: Changelog | C9: Trust and freshness | D9: Article per entry | E9: Method and data source releases
A10: /calculators/max-bid | B10: Max bid calculator | C10: auction max bid calculator, buyer's premium calculator | D10: WebApplication | E10: Free public calculator from tab 10. Strong link magnet
A11: /calculators/gst-auction | B11: GST on auction purchases | C11: GST on auction items Australia | D11: WebApplication, FAQPage | E11: Free calculator with plain explanation and not tax advice note
A12: /auctions/grays | B12: Grays guide | C12: Grays buyer's premium, how to buy on Grays | D12: Article, FAQPage | E12: One guide per supported auction house. Premium facts dated and sourced
A13: /auctions/pickles | B13: Pickles guide | C13: As above for Pickles | D13: Article, FAQPage
A14: /auctions/lloyds | B14: Lloyds guide | C14: As above for Lloyds | D14: Article, FAQPage
A15: /breakdowns | B15: Auction Breakdowns hub | C15: Undervalued auction lots this week | D15: CollectionPage | E15: Weekly breakdowns (tab 37)
A16: /breakdowns/[slug] | B16: Auction Breakdown | C16: Specific auction name and category | D16: Article | E16: Top lots with estimates, confidence and links. No copied photos
A17: /value/[category]/[brand]/[model] | B17: Value guide | C17: [brand] [model] price guide Australia, used [model] value | D17: WebPage, Dataset, BreadcrumbList | E17: Programmatic pages (tab 35)
A18: /value/[category] | B18: Category hub | C18: Used [category] prices Australia | D18: CollectionPage, BreadcrumbList | E18: Links every guide in the category
A19: /learn | B19: Learn hub | C19: Auction buying guides | D19: CollectionPage | E19: Evergreen guides and glossary
A20: /learn/glossary/[term] | B20: Glossary term | C20: What is hammer price, buyer's premium, passed in | D20: DefinedTerm, Article | E20: Short answer first definitions. High AI citation potential
A21: /learn/[guide] | B21: Guide | C21: How to flip auction items, how to inspect used machinery | D21: Article | E21: Written with real examples and our data
A22: /compare/[alternative] | B22: Comparison | C22: MaxBid vs manual research, vs eBay Product Research | D22: Article | E22: Fair, factual comparisons
A23: /about | B23: About | C23: Brand and founders | D23: AboutPage, Organization, Person | E23: Founder story, real people, Perth based. E E A T signal
A24: /contact, /legal/* | B24: Contact and legal | C24: Trust | D24: ContactPage | E24: Terms, privacy, disclaimers from tabs 20 and 30
A26: Technical SEO checklist
A27: ID | B27: Area | C27: Requirement
A28: TS01 | B28: Rendering | C28: Static generation or incremental regeneration for every public page. No client only content.
A29: TS02 | B29: Metadata | C29: Unique title and description per page through the Next.js metadata API. Titles under 60 characters.
A30: TS03 | B30: Canonicals | C30: Self referencing canonical on every page. Parameter URLs canonicalised.
A31: TS04 | B31: Sitemaps | C31: Segmented sitemaps for static pages, breakdowns, value guides and glossary, regenerated on publish.
A32: TS05 | B32: Robots | C32: App subdomain noindex and disallowed. Crawler policy from tab 36.
A33: TS06 | B33: Locale | C33: html lang en AU, Australian spelling, AUD prices, Australian business details in Organization schema.
A34: TS07 | B34: Core Web Vitals | C34: LCP under 2.5s, INP under 200ms, CLS under 0.1 at the 75th percentile.
A35: TS08 | B35: Images | C35: next/image, AVIF or WebP, explicit dimensions, descriptive alt text.
A36: TS09 | B36: Internal links | C36: Breadcrumbs on every page. Guides link to category hubs, related models and the calculator. Breakdowns link to value guides.
A37: TS10 | B37: Structured data | C37: JSON LD per page type in the table above, validated in CI.
A38: TS11 | B38: Open Graph | C38: Generated share image, title and description for every page.
... A42: TS15 | B42: Security | C42: HTTPS only, HSTS, no mixed content.

Sheet 35 Value Guides
A1: Value Guides (Programmatic SEO)
A2: Phase 2. Built only from our own aggregated data.
A3: Page template
A4: Title pattern | B4: [Brand] [Model] used price guide Australia [Year]
A5: Answer first | B5: Opening sentence states the typical used price range in AUD, the evidence count and the date. Written so it can be quoted on its own.
A6: Data blocks | B6: Typical used range, recent auction results range, new price where known, price trend chart, evidence count by type, confidence label.
A7: Specifications | B7: Model specifications from product_spec_sources with source links and the DS23 note.
A8: What changes the value | B8: Options, hours, condition and age factors known for the model or category.
A9: Buying checklist | B9: Category We cannot verify items reframed as what to check before bidding.
A10: Related | B10: Similar models, category hub, max bid calculator, current lots of this model in supported auctions.
A11: Call to action | B11: Analyse a lot of this model. Set an alert for this model (later phase).
A12: FAQ | B12: Three to five short answer questions using real data, such as how much a used [Model] sells for at auction in Australia.
A13: Disclaimer | B13: DS02 style note and method version on every page.
A15: Publish rules
A16: Minimum evidence | B16: At least 5 priced comparables including at least 2 sold or realised results in the last 12 months before a page is indexable.
A17: Below threshold | B17: Page may exist for users but is noindex and excluded from sitemaps.
A18: Uniqueness | B18: Every indexable page must show figures unique to that model. No boilerplate only pages.
A19: Refresh | B19: Rebuilt weekly or when new evidence arrives. Last updated date shown.
A20: Data source rule | B20: Aggregated figures only. No copied listing text, no third party photos, no individual private seller details.
A21: Trade marks | B21: Brand and model names used only to identify the product. No logos. Note that the platform is not affiliated with the manufacturer.
A22: Quality review | B22: Templates reviewed by a person before rollout. Random sample of 20 pages reviewed each month.

Sheet 36 AI Search
A1: AI Search Visibility
A2: Goal: be the source AI answers cite for Australian auction pricing questions. Verify crawler names before launch (O13).
A3: User agent | B3: Provider | C3: Purpose | D3: Policy
A4: OAI-SearchBot | B4: OpenAI | C4: Search and answers | D4: Allow
A5: ChatGPT-User | B5: OpenAI | C5: User requested fetch | D5: Allow
A6: GPTBot | B6: OpenAI | C6: Model training | D6: Block
A7: Claude-SearchBot | B7: Anthropic | C7: Search and answers | D7: Allow
A8: Claude-User | B8: Anthropic | C8: User requested fetch | D8: Allow
A9: ClaudeBot | B9: Anthropic | C9: Model training | D9: Block
A10: PerplexityBot | B10: Perplexity | C10: Search and answers | D10: Allow
A11: Perplexity-User | B11: Perplexity | C11: User requested fetch | D11: Allow
A12: Googlebot | B12: Google | C12: Search including AI Overviews | D12: Allow
A13: Google-Extended | B13: Google | C13: Gemini training and grounding control | D13: Block
A14: Bingbot | B14: Microsoft | C14: Search, also used by Copilot and others | D14: Allow
... A16: CCBot | B16: Common Crawl | C16: Dataset used for training | D16: Block
A17: Trade off: blocking training crawlers protects our data but may reduce how well future models know the brand. Review after launch.
A19: How we earn citations
A20: ID | B20: Tactic | C20: Detail
A21: G01 | B21: Answer first writing | C21: Every guide, glossary term and value guide opens with a one or two sentence direct answer that stands alone.
A22: G02 | B22: Citable facts | C22: Dated, sourced numbers such as typical ranges, premium rates and accuracy stats, presented in plain HTML tables and lists.
A23: G03 | B23: Public methodology | C23: The methodology, accuracy and changelog pages explain exactly how figures are made. AI engines favour sources that show their working.
A24: G04 | B24: Question coverage | C24: FAQ sections target real questions: how much is buyer's premium on Grays, do you pay GST at auction, what is a used edgebander worth.
A25: G05 | B25: Entity consistency | C25: Same name, description, location and founders across the site, schema, social profiles and directories.
A26: G06 | B26: Third party mentions | C26: Useful presence in reseller communities, YouTube and industry sites. AI answers weigh what others say about us.
A27: G07 | B27: Freshness | C27: Visible last updated dates and weekly breakdowns signal current data.
A28: G08 | B28: Clean structure | C28: Semantic headings, tables and definition lists. No key facts hidden in images or scripts.
A29: G09 | B29: llms.txt | C29: Publish an llms.txt listing key pages. Low cost, uncertain benefit, easy to maintain.
A30: G10 | B30: Measurement | C30: Track a fixed set of 30 prompts across major AI engines monthly and record citations (O15).

Sheet 37 Marketing
A1: Marketing and Go to Market
A3: Channels
A4: Organic search | B4: Value guides, calculators, auction house guides and glossary. Long term primary channel.
A5: AI answers | B5: Methodology, accuracy and answer first content per tab 36.
A6: Communities | B6: Reseller Facebook groups, YouTube, Reddit and trade forums. Give real answers and breakdowns. Follow each group's rules. No spam.
A7: Email | B7: Weekly Auction Breakdown newsletter. Owned audience from day one.
A8: Referral | B8: Both organisations receive bonus credits after the referred organisation's first payment.
A9: Paid | B9: Deferred until conversion rates are proven. Then retargeting and branded search first.
A11: Auction Breakdown format
A12: Cadence | B12: Weekly, published midweek before weekend closes.
A13: Content | B13: One upcoming catalogue. Top ten lots by opportunity score with estimate range, confidence, rough max bid and a link to the lot.
A14: Outputs | B14: Web page, newsletter, short social clips of the lots and figures, community post summary.
A15: Rules | B15: No copied photos or listing text. Standard disclaimers. Figures from triage clearly labelled as rough.
A16: Call to action | B16: Run your own numbers on these lots with a free account.
A18: Launch plan
A19: Now to Week 1 | B19: Lock name and domains. Holding page with waitlist live.
A20: Build weeks | B20: Share build progress and early breakdowns with the waitlist.
A21: Month 3 | B21: Marketing site, try before sign up, first four breakdowns.
A22: Month 4 | B22: Founding member offer to the waitlist (O14), then public launch.
A23: After launch | B23: Value guides roll out as data thresholds are met.
A25: Lifecycle email
A26: Email | B26: Trigger | C26: Content
A27: Welcome | B27: Sign up | C27: Three step setup and first analysis prompt
A28: First result | B28: Triage complete | C28: What your top lots mean and how to shortlist
A29: Nudge | B29: No deep analysis after 3 days | C29: Try one lot free using starter credits
A30: Closing soon | B30: Watchlist trigger | C30: Transactional alert with target and maximum
A31: Outcome reminder | B31: Lot closed | C31: Record the result to sharpen future estimates
A32: Monthly recap | B32: Monthly | C32: Lots analysed, won, margin achieved
A33: Win back | B33: 30 days inactive | C33: Latest breakdown and what is new

Sheet 38 UX Standards
A1: UX Standards
A3: Try before sign up
A4: Flow | B4: Visitor pastes a supported catalogue URL on the homepage. If the auction is already triaged in shared data, show the top five lots with ranges and rough max bids. Remaining lots blurred behind sign up.
A5: New auctions | B5: Queue triage and ask for an email to send results. This builds the waitlist and controls cost.
A6: Limits | B6: Rate limited per hashed IP. Bot protection. Deep analysis never available anonymously.
A8: Onboarding
A9: Step 1 | B9: GST registered yes or no, with a one line plain explanation.
A10: Step 2 | B10: Base location for transport estimates.
A11: Step 3 | B11: Profit target in dollars or percentage, with a sensible default.
A12: Guided first analysis | B12: Paste a catalogue or use a sample. Inline tips at triage, shortlist and the calculator. Tips dismiss permanently.
A13: Target | B13: Sign up to first triage result in under five minutes.
A15: Interface states
A16: Empty states | B16: Every empty screen explains what goes there and gives one clear action.
A17: Loading | B17: Skeletons shaped like the final content. Stop line loader for background jobs with stage names.
A18: Errors | B18: Say what happened, what we did and what the user can do. Never blame the user. Money related errors stay plain.
A19: Partial results | B19: Lots appear as they complete. Failed lots show retry and refund status.
A20: Offline and slow | B20: Mobile bid view caches the watchlist so figures remain visible with poor reception at auction yards.
A22: Interaction
A23: Keyboard | B23: J and K move between lots, S shortlists, W watchlists, forward slash searches, question mark shows shortcuts.
A24: Undo | B24: Exclusions, overrides and shortlist changes offer undo for ten seconds.
A25: Instant feedback | B25: Calculator changes update figures within 100ms.
A26: Touch | B26: Targets at least 44px on mobile. Bid view usable one handed.
A27: Microcopy | B27: Buttons say what they do: Analyse 12 lots (12 credits), not Submit.
A29: Accessibility (WCAG 2.2 AA)
A30: Contrast | B30: 4.5 to 1 for text and 3 to 1 for UI elements in both themes.
A31: Status | B31: Never colour alone. Every zone and badge has a text label.
A32: Keyboard | B32: Every function reachable by keyboard with a visible focus ring.
A33: Screen readers | B33: Tables with proper headers, live regions for recalculated bid figures, labelled sliders with value text.
A34: Motion | B34: Reduced motion respected everywhere.
A35: Target size | B35: Minimum 24px targets per WCAG 2.2, 44px on mobile by our standard.
A37: Testing
A38: Usability rounds | B38: Five real resellers per round at the end of Weeks 4 and 7 and before public launch.
A39: Tasks | B39: Analyse a catalogue, shortlist, adjust costs, read the evidence, use the bid view.
A40: Measures | B40: Task success, time on task, errors and a confidence rating after reading a lot.
A41: Automated | B41: axe accessibility checks and Lighthouse budgets in CI.

Sheet 39 Build Architecture
A1: Build Architecture
A2: Library first, mobile first, small files. These rules apply to every line of code, human or AI written.
A3: Principles
A4: ID | B4: Principle | C4: Rule
A5: BA01 | B5: Library first | C5: Check packages/ui before writing any UI. If a component exists, use it. If it nearly fits, extend it with a prop. Build a new one only when nothing fits, and build it in Storybook first.
A6: BA02 | B6: Thin pages | C6: A page file handles routing, metadata and data loading, then imports sections. No styling or business logic in pages.
A7: BA03 | B7: One job per file | C7: One component per file. Hooks, types, constants and helpers in their own files.
A8: BA04 | B8: Single sources of truth | C8: Bid maths in packages/calc. Colours, type and spacing in packages/tokens. Disclaimer and message text in packages/content. Nothing is retyped.
A9: BA05 | B9: Server first | C9: Server components by default. Client components only for interactive leaves such as the bid slider, auction room and docket inputs.
A10: BA06 | B10: Mobile first | C10: Every component is designed and built for a 360px screen first, then enhanced for larger screens.
A11: BA07 | B11: Tokens only | C11: No hex values, pixel font sizes or ad hoc spacing inside components. Everything references tokens.
A12: BA08 | B12: Budgets are gates | C12: File size, bundle size and Core Web Vitals budgets fail the build when broken.
A14: Monorepo structure (Turborepo, pnpm)
A15: Path | B15: Purpose | C15: Contains | D15: Notes
A16: apps/web | B16: Public site at maxbid.com.au | C16: Marketing pages, calculators, value guides, breakdowns | D16: Imports sections from packages/ui. Mostly static and server rendered.
A17: apps/app | B17: Product at app.maxbid.com.au | C17: Triage, lot detail, docket, watchlist, bid view, settings | D17: Installable web app. noindex.
A18: packages/tokens | B18: Design tokens | C18: CSS variables, Tailwind preset, light and dark themes | D18: Tab 17 and 33 values live here only.
A19: packages/ui | B19: Component library | C19: Primitives, composites and sections | D19: Catalogued in Storybook.
A20: packages/calc | B20: Bid engine | C20: Bid limits, GST, cost totals, scenarios, confidence | D20: Pure TypeScript, no UI. Tested against tab 10.
A21: packages/content | B21: Words | C21: Disclaimer library, standard phrases, glossary definitions | D21: DS01 to DS35 as named exports.
A22: packages/db | B22: Data access | C22: Supabase generated types, typed queries, RLS test helpers | D22: Generated type files exempt from line limits.
A23: packages/config | B23: Shared config | C23: ESLint, TypeScript, Prettier, Vitest and Playwright settings | D23: Line limits defined once here.
A24: apps/storybook | B24: Catalogue | C24: Stories for every library component | D24: Deployed privately for review.
A26: Component layers
A27: Layer | B27: Location | C27: What it is | D27: Examples
A28: 1 Tokens | B28: packages/tokens | C28: Colour, type, spacing, radius, motion, breakpoints | D28: Changed only by design decision
A29: 2 Primitives | B29: packages/ui/primitives | C29: Smallest building blocks with no business meaning | D29: Button, Input, Money, Badge
A30: 3 Composites | B30: packages/ui/composites | C30: Primitives combined into a reusable product element | D30: BidRail, EvidenceRow, Docket
A31: 4 Sections | B31: packages/ui/sections | C31: A full band of a page built from composites | D31: SheetHero, ClosingList
A32: 5 Shells | B32: apps/*/app/layout.tsx | C32: Header, footer, navigation and theme around pages | D32: One marketing shell, one app shell
A33: 6 Pages | B33: apps/*/app/**/page.tsx | C33: Imports sections, sets metadata, loads data | D33: 80 lines maximum
A35: Component inventory
A36: ID | B36: Component | C36: Layer | D36: Used in | E36: Notes
A37: UI01 | B37: Button | C37: Primitive | D37: Both | E37: Primary marker yellow, secondary outline, ghost, danger. Loading and disabled states. 44px minimum height
A38: UI02 | B38: Input | C38: Primitive | D38: Both | E38: Text, number, URL, email. Label, hint, error. Mono variant for figures
A39: UI03 | B39: Toggle group | C39: Primitive | D39: Both | E39: GST registered, monthly or annual, theme. aria pressed
A40: UI04 | B40: Money | C40: Primitive | D40: Both | E40: Formats AUD with tabular figures, parentheses for negatives, size variants up to hero
A41: UI05 | B41: MonoLabel | C41: Primitive | D41: Both | E41: Uppercase mono data label
A42: UI06 | B42: ProvenanceTag | C42: Primitive | D42: Both | E42: Verified, Extracted, Estimated, Your input
A43: UI07 | B43: AiLabel | C43: Primitive | D43: Both | E43: AI generated marker
A44: UI08 | B44: MatchBadge | C44: Primitive | D44: Both | E44: Six match levels
A45: UI09 | B45: ConfidenceBadge | C45: Primitive | D45: Both | E45: High, Medium, Low, Insufficient with score
A46: UI10 | B46: ZoneLabel | C46: Primitive | D46: Both | E46: On target, Below target, Loss risk. Text plus colour
A47: UI11 | B47: InfoNote | C47: Primitive | D47: Both | E47: Muted 12px note with info icon. Reads text from packages/content
... A86: UI50 | B86: BidView | C86: Section | D86: App | E86: Mobile bid cards with offline cache indicator
A88: File size rules
A89: ID | B89: Applies to | C89: Limit | D89: Enforcement
A90: FS01 | B90: Any code file | C90: 300 lines hard cap, 150 target | D90: ESLint max-lines, blank lines and comments excluded. CI fails above cap.
A91: FS02 | B91: Page file | C91: 80 lines | D91: If a page grows, move content into a section.
A92: FS03 | B92: Function or component body | C92: 80 lines | D92: ESLint max-lines-per-function.
A93: FS04 | B93: Props | C93: Around 10 props per component | D93: More suggests splitting into smaller components.
A94: FS05 | B94: Nesting | C94: JSX nesting depth of 6 or less | D94: Deeper trees become child components.
A95: FS06 | B95: Exemptions | C95: Generated Supabase types and lockfiles only | D95: Listed in lint config. No other exceptions.
A96: FS07 | B96: Imports | C96: Import components by path, avoid root barrel files | D96: Keeps bundles tree shaken and small.
A98: Component file pattern
A99: Folder per component | B99: packages/ui/composites/Docket/ holding Docket.tsx, Docket.stories.tsx, Docket.test.tsx, docket.types.ts, index.ts, plus child parts such as DocketLine.tsx.
A100: Stories required | B100: Default, every state and variant, light and dark theme, 375px and 1440px viewports, long content and empty content.
A101: Definition of done | B101: Tokens only, stories complete, axe check passes in the Storybook test runner, unit tests for any logic, under the line caps, props documented, visual snapshot approved.
A103: Mobile first rules
A104: ID | B104: Rule | C104: Detail
A105: MF01 | B105: Base width | C105: Author for 360px first. Enhance at 640, 768, 1024 and 1280px with min width queries only.
A106: MF02 | B106: Test viewports | C106: 375 iPhone SE, 393 iPhone 15, 412 Pixel, 820 iPad, 1280 and 1440 desktop in every story and Playwright run.
A107: MF03 | B107: Touch | C107: 44px targets, no hover only actions, swipe between lots in bid view, thumb reachable primary actions.
A108: MF04 | B108: Layout patterns | C108: Desktop split views become full screen sheets on mobile. Tables become stacked rows with the key figure first. Sticky bottom action bar for the main action.
A109: MF05 | B109: Viewport | C109: Dynamic viewport units, safe area insets for notches and home bars, no fixed 100vh.
A110: MF06 | B110: Installable app | C110: Manifest with standalone display, maskable icons, theme colour, install prompt after first analysis.
A111: MF07 | B111: Offline | C111: Service worker caches app shell, watchlist and bid view data. Shows last synced time when offline.
A112: MF08 | B112: Input | C112: Correct keyboard types for money, email and URL fields. Paste friendly URL field.
A113: MF09 | B113: Performance on phones | C113: Test on a mid range Android over throttled 4G. Budgets below must hold there.
A114: MF10 | B114: Desktop parity | C114: Desktop gets density, keyboard shortcuts and split views. No feature is desktop only or mobile only unless listed in tab 07.
A116: Performance budgets
A117: ID | B117: Metric | C117: Budget | D117: Measured by
A118: PB01 | B118: Marketing page first load JavaScript | C118: 130 KB gzipped | D118: size-limit in CI
A119: PB02 | B119: App route first load JavaScript | C119: 200 KB gzipped | D119: size-limit in CI
A120: PB03 | B120: Largest Contentful Paint | C120: Under 2.5s at 75th percentile on mobile | D120: Search Console and Vercel analytics
A121: PB04 | B121: Interaction to Next Paint | C121: Under 200ms | D121: As above
A122: PB05 | B122: Cumulative Layout Shift | C122: Under 0.1 | D122: As above
A123: PB06 | B123: Lighthouse mobile performance | C123: 90 or above on key pages | D123: Lighthouse CI
A124: PB07 | B124: Below the fold interactive sections | C124: Lazy loaded with next/dynamic | D124: Code review
A125: PB08 | B125: Fonts | C125: Three families, subset, self hosted, preloaded | D125: next/font
A127: AI assisted build rules (CLAUDE.md and AGENTS.md)
A128: ID | B128: When | C128: Rule
A129: AR01 | B129: Before building UI | C129: Search packages/ui and Storybook for an existing component and use it.
A130: AR02 | B130: New component | C130: Create it in packages/ui with stories and tests first, then use it in the page.
A131: AR03 | B131: Size | C131: Never exceed 300 lines. Split the file before adding to it.
A132: AR04 | B132: Maths | C132: Never reimplement bid maths. Import from packages/calc.
A133: AR05 | B133: Words | C133: Never type disclaimer text. Import from packages/content.
A134: AR06 | B134: Styling | C134: Tokens only. No hex values or arbitrary Tailwind values.
A135: AR07 | B135: Client code | C135: Add use client only to the smallest interactive component that needs it.
A136: AR08 | B136: Mobile | C136: Write mobile styles first and check the story at 375px before 1440px.
A137: AR09 | B137: Checks | C137: Run lint, type check, unit tests and Storybook tests before finishing a task.
